Workbook

Sheet Historique
B1: En millions | G1: Répartition par canton
B2: Bénéfice | C2: Chiffre affaires (OFJ) | D2: RBJ | E2: PBJ | F2: Source | G2: FR | H2: VD | I2: GE | J2: NE | K2: VS | L2: JU | M2: N° | N2: Note
A3: 1938 | B3: =1.154942+0.56164264+0.412947 -> 2.1295316 | E3: =0.95494+0.56164264 -> 1.5165826 | F3: Courrier de Genève, Volume 71, Numéro 29, 30 janvier 1938, L'impartial, 16 juillet 1938, La Gruyère, 17 septembre 1938 | G3: =105676+74677.32 -> 180353.32 | H3: =388438+203986 -> 592424 | I3: =176267+123099+80041 -> 379407 | J3: =176693+100868 -> 277561 | K3: =107866+59010+47655 -> 214531 | M3: 46082 | N3: première loterie
A4: 1939
A5: 1940 | C5: 9 | F5: OFJ
A6: 1941
A7: 1942
A8: 1943
A9: 1944
A10: 1945
A11: 1946
A12: 1947
A13: 1948
A14: 1949
A15: 1950 | C15: 6.2 | F15: OFJ
A16: 1951
A17: 1952
A18: 1953
A19: 1954
A20: 1955
A21: 1956
A22: 1957
A23: 1958
A24: 1959
A25: 1960 | C25: 7.8 | F25: OFJ
A26: 1961
A27: 1962
A28: 1963
A29: 1964
A30: 1965
A31: 1966
A32: 1967
A33: 1968
A34: 1969
A35: 1970 | C35: 10.68 | F35: OFJ
A36: 1971
A37: 1972
A38: 1973
A39: 1974
A40: 1975
A41: 1976
A42: 1977
A43: 1978
A44: 1979 | L44: 145786 | N44: FAN - L'express, 3 octobre 1980
A45: 1980 | B45: 16 | C45: 18.9 | F45: La tribune de Genève, Numéro 219, 21 septembre 1982, OFJ | I45: 1004500 | J45: 1301428 | L45: 344200 | N45: L'impartial, 17 mai 1989, La tribune de Genève, Numéro 93, 22 avril 1980, L'impartial, 7 février 1981
A46: 1981 | B46: 21.2 | F46: Journal du Jura, Volume 120, Numéro 160, 12 juillet 1983 | J46: 1416246 | L46: 498000 | N46: FAN - L'express, 19 février 1982, L'impartial, 18 août 1982
A47: 1982 | B47: 22.217985 | F47: Journal du Jura, Volume 120, Numéro 160, 12 juillet 1983, Le Franc-Montagnard, Volume 84, Numéro 12192, 22 juillet 1983 | G47: 1729502 | H47: 6385807 | I47: 3789140 | J47: 1895914 | K47: 2524289 | L47: 675344 | N47: L'impartial, 2 février 1983, Le Franc-Montagnard, Volume 84, Numéro 12192, 22 juillet 1983
A48: 1983
A49: 1984 | E49: 21.3 | I49: 954760 | J49: 2007696 | N49: La tribune de Genève, Numéro 100, 30 avril 1984, FAN - L'express, 20 juin 1986, FAN - L'express, 12 avril 1985
A50: 1985 | E50: 22.2 | J50: 1999551 | L50: 431900 | N50: L'impartial, 14 mai 1986, FAN - L'express, 20 juin 1986, L'impartial, 23 août 1986
A51: 1986 | B51: 23 | C51: 16.5 | F51: Le nouvelliste, Volume 30, Numéro 233, 9 octobre 1997, FAN - L'express, 3 juin 1987 | J51: 2330900 | N51: L'impartial, 12 octobre 1987
A52: 1987 | B52: 29.8 | C52: 27 | F52: La tribune de Genève, Numéro nº 135/24, 13 juin 1989 | G52: 1700000 | I52: 6300000 | J52: 2746751 | N52: FAN - L'express, 4 juin 1988, La liberté, 25 mai 1988, Courrier de Genève, Volume 121, Numéro 134, 13 juin 1989
A53: 1988 | B53: 32 | E53: 25.4 | F53: L'impartial, 17 mai 1989, Journal du Jura, Volume 126, Numéro 135, 13 juin 1989, La tribune de Genève, Numéro nº 135/24, 13 juin 1989 | J53: 1653090 | L53: 1500000 | N53: FAN - L'express, 14 février 1989, L'impartial, 17 mai 1989
A54: 1989 | K54: 5000000 | L54: 1090000 | N54: Le nouvelliste, Numéro 62, 15 mars 2003, L'impartial, 7 octobre 1991
A55: 1990 | C55: 45.6 | F55: OFJ | G55: =1300000+1512000 -> 2812000 | J55: 2666920 | L55: 874000 | N55: 104e La Gruyère, 21 juin 1990, 105e, La liberté, 30 novembre 1990, L'impartial, 3 juin 1991, L'impartial, 7 octobre 1991
A56: 1991 | B56: 50 | C56: 64.091421 | E56: 34.8 | F56: OFJ, La tribune de Genève, Numéro nº 176-30, 29 juillet 2000 | G56: 1009400 | H56: 13200000 | I56: 7400000 | N56: 107e, La Gruyère, 12 décembre 1991, Courrier de Genève, Volume 124, Numéro 34, 11 février 1992, La tribune de Genève, Numéro nº 34/7, 11 février 1992
A57: 1992 | C57: 100.32544 | G57: 1156000 | L57: 1600000 | N57: 109e, La liberté, 10 décembre 1992
A58: 1993 | B58: 46 | C58: 135.39467 | F58: L'impartial, 14 novembre 1994, Le nouvelliste, Volume 27, Numéro 182, 9 août 1994 | J58: 4000000 | K58: 7500000 | L58: 1676701 | N58: Le nouvelliste, Volume 27, Numéro 259, 9 novembre 1994, L'impartial, 14 novembre 1994, Le Franc-Montagnard, Volume 95, Numéro 13897, 9 décembre 1994
A59: 1994 | C59: 176.37012 | F59: Le nouvelliste, Volume 28, Numéro 174, 28 juillet 1995
A60: 1995 | B60: 60 | C60: 212.77054 | F60: L'impartial, 30 octobre 2001 | G60: 5900000 | H60: 23000000 | I60: 11300000 | J60: 6600000 | K60: 10200000 | L60: 2500000 | N60: Le nouvelliste, Volume 29, Numéro 160, 12 juillet 1996
A61: 1996 | B61: 69 | C61: 227.60497 | F61: L'impartial, 28 juin 1997, Le nouvelliste, Volume 30, Numéro 233, 9 octobre 1997 | G61: 4200000 | H61: 26800000 | I61: 9700000 | J61: 5700000 | K61: 8000000 | L61: 2200000 | N61: L'impartial, 28 juin 1997
A62: 1997 | B62: 79.8 | C62: 239.59665 | F62: La liberté, 3 juillet 1998 | G62: 7800000 | H62: 29500000 | J62: 13800000 | L62: 3200000 | N62: Le nouvelliste, Volume 30, Numéro 233, 9 octobre 1997
A63: 1998 | B63: 84 | C63: 249.87761 | F63: La tribune de Genève, Numéro nº 176-30, 29 juillet 2000, FAN - L'express, 10 juillet 1999 | G63: 8000000 | H63: 31400000 | I63: 14400000 | J63: 8000000 | K63: 14000000 | L63: 3466950 | N63: Le Franc-Montagnard, Volume 100, Numéro 14701, 2 août 2000, Le Franc-Montagnard, Volume 100, Numéro 14554, 28 juillet 1999
A64: 1999 | B64: 100.60404 | C64: 276.50096 | F64: La tribune de Genève, Numéro nº 176-30, 29 juillet 2000 | L64: 4189042 | N64: Le Franc-Montagnard, Volume 100, Numéro 14701, 2 août 2000
A65: 2000 | B65: 111 | C65: 323.3736 | F65: L'impartial, 30 octobre 2001
A66: 2001 | B66: 135 | C66: 380.83245 | F66: FAN - L'express, 5 juillet 2002
A67: 2002 | B67: 143.5 | C67: 1300 | E67: 136.4 | F67: Le Franc-Montagnard, Volume 105, Numéro 15118, 8 juillet 2003 | K67: 24190588 | N67: Le nouvelliste, Numéro 62, 15 mars 2003, Le nouvelliste, Numéro 211, 13 septembre 2003
A68: 2003 | B68: 175 | C68: 1255.7895 | F68: Le nouvelliste, Numéro 149, 30 juin 2004
A69: 2004 | B69: 172 | C69: 1320.2996 | F69: RA
A70: 2005 | B70: 178.4 | C70: 1329.625 | F70: RA
A71: 2006 | B71: 188.5 | C71: 1292.7353 | F71: RA
A72: 2007 | B72: 174.2 | C72: 1319.3569 | F72: RA
A73: 2008 | B73: 183.2 | C73: 1410.6657 | F73: RA
A74: 2009 | B74: 190.7 | C74: 1403.3061 | F74: RA
A75: 2010 | B75: 198.7 | C75: 1599.0178 | D75: 357.91755 | F75: RA, OFJ
A76: 2011 | B76: 203.3 | C76: 1620.9946 | D76: 370.25264 | F76: RA, OFJ
A77: 2012 | B77: 203 | C77: 1581.5613 | D77: 367.0248 | F77: RA, OFJ
A78: 2013 | B78: 206 | C78: 1612.6556 | D78: 377.73525 | F78: RA, OFJ | G78: ='Détail'!F2 -> 16904793 | H78: ='Détail'!D2 -> 33217743 | I78: ='Détail'!L2 -> 22938216 | J78: ='Détail'!J2 -> 13286650 | K78: ='Détail'!H2 -> 23832371 | L78: ='Détail'!N2 -> 5900967 | N78: RA
A79: 2014 | B79: 209.9 | C79: 1610.1129 | D79: 387.64196 | F79: RA, OFJ | G79: 14672240 | H79: ='Détail'!D11 -> 36880059 | I79: 25764723 | J79: 13549800 | K79: ='Détail'!H11 -> 26149635 | L79: ='Détail'!N11 -> 5355635 | N79: RA
A80: 2015 | B80: 209.5 | C80: 1586.5352 | D80: 398.33904 | F80: RA, OFJ | G80: 14478414 | H80: ='Détail'!D20 -> 34153502 | I80: 32285500 | J80: 12954500 | K80: ='Détail'!H20 -> 23251870 | L80: ='Détail'!N20 -> 5140195 | N80: RA
A81: 2016 | B81: 216.8 | C81: 1642.256 | D81: 398.33904 | F81: RA, OFJ | G81: 17316651 | H81: ='Détail'!D29 -> 34846396 | I81: 28579210 | J81: 13302310 | K81: ='Détail'!H29 -> 25143905 | L81: ='Détail'!N29 -> 5767420 | N81: RA
A82: 2017 | B82: 216.2 | C82: 1570.7739 | D82: 386.48653 | F82: RA, OFJ | G82: 17156388 | H82: ='Détail'!D38 -> 40437100 | I82: 32102825 | J82: 14360550 | K82: ='Détail'!H38 -> 27088102 | L82: ='Détail'!N38 -> 6639316 | N82: RA
A83: 2018 | B83: 216.4 | C83: 1576.4331 | D83: 387.96251 | F83: RA, OFJ | G83: 19944842 | H83: ='Détail'!D47 -> 38632360 | I83: 40630366 | J83: 15770200 | K83: ='Détail'!H47 -> 33255111 | L83: ='Détail'!N47 -> 5759651 | N83: RA
A84: 2019 | B84: 224.3 | F84: RA | G84: 19802308 | H84: ='Détail'!D56 -> 41258170 | I84: 27092160 | J84: 14023950 | K84: ='Détail'!H56 -> 30277691 | L84: ='Détail'!N56 -> 5742465 | N84: RA
A85: 2020 | B85: 224.7 | F85: RA | G85: 19152190 | H85: ='Détail'!D65 -> 38139600 | I85: 31155300 | J85: 12845350 | K85: ='Détail'!H65 -> 20402610 | L85: ='Détail'!N65 -> 5660787 | N85: RA
A86: 2021 | B86: 235 | F86: RA | G86: 20134371 | H86: ='Détail'!D74 -> 31055090 | I86: 35737415 | J86: 10213450 | K86: ='Détail'!H74 -> 31858269 | L86: ='Détail'!N74 -> 4126790 | N86: RA
A87: 2022 | B87: 243.4 | F87: RA | G87: 22557977 | H87: ='Détail'!D83 -> 32104500 | I87: 35208336 | J87: 11650300 | K87: ='Détail'!H83 -> 30190866 | L87: ='Détail'!N83 -> 4157250 | N87: RA
A88: 2023 | B88: 243.7 | F88: RA | G88: 27037002 | H88: ='Détail'!D92 -> 62644138 | I88: 53014828 | J88: 16838496 | K88: ='Détail'!H92 -> 34858894 | L88: ='Détail'!N92 -> 7174672 | N88: RA
A89: 2024 | B89: 258.23616 | F89: RA | G89: 29232206 | H89: ='Détail'!D101 -> 63649163 | I89: 46560474 | J89: 16833520 | K89: ='Détail'!H101 -> 36909515 | L89: ='Détail'!N101 -> 7589795 | N89: RA
A90: 2025 | B90: 252.00529 | F90: RA | G90: 28471510 | H90: ='Détail'!D110 -> 79706647 | I90: 44562014 | J90: 15529120 | K90: ='Détail'!H110 -> 41354730 | L90: ='Détail'!N110 -> 8711666 | N90: RA

Sheet Total
C1: 2000 | D1: 2001 | E1: 2002 | F1: 2003 | G1: 2004 | H1: 2005 | I1: 2006 | J1: 2007 | K1: 2008 | L1: 2009 | M1: 2010 | N1: 2011 | O1: 2012 | P1: 2013 | Q1: 2014 | R1: 2015 | S1: 2016 | T1: 2017 | U1: 2018 | V1: 2019 | W1: 2020 | X1: 2021 | Y1: 2022 | Z1: 2023 | AA1: 2024 | AB1: 2025
B2: Produit brut des jeux en Suisse (milions) | C2: =If(C5+C29+C37=0, " ",C5+C29+C37) | D2: =If(D5+D29+D37=0, " ",D5+D29+D37) | E2: =If(E5+E29+E37=0, " ",E5+E29+E37) | F2: =If(F5+F29+F37=0, " ",F5+F29+F37) -> 421 | G2: =If(G5+G29+G37=0, " ",G5+G29+G37) -> 489 | H2: =If(H5+H29+H37=0, " ",H5+H29+H37) -> 548 | I2: =If(I5+I29+I37=0, " ",I5+I29+I37) -> 582 | J2: =If(J5+J29+J37=0, " ",J5+J29+J37) -> 532 | ... AB2: =If(AB5+AB29+AB37=0, " ",AB5+AB29+AB37) -> 429.82499
B3: Distribué aux cantons, confédération etc. | C3: =if(C8+C31+C43=0, " ",C8+C31+C43) | D3: =if(D8+D31+D43=0, " ",D8+D31+D43) | E3: =if(E8+E31+E43=0, " ",E8+E31+E43) | F3: =if(F8+F31+F43=0, " ",F8+F31+F43) | G3: =if(G8+G31+G43=0, " ",G8+G31+G43) -> 172 | H3: =if(H8+H31+H43=0, " ",H8+H31+H43) -> 178.4 | I3: =if(I8+I31+I43=0, " ",I8+I31+I43) -> 188.5 | J3: =if(J8+J31+J43=0, " ",J8+J31+J43) -> 174.2 | ... AB3: =if(AB8+AB31+AB43=0, " ",AB8+AB31+AB43) -> 252.00529
A5: Loro | B5: Produit brut des jeux (milions) | L5: 371 | M5: 358 | N5: 370 | O5: 367.02483 | P5: ='Détail'!P8/1000000 -> 377.73526 | Q5: ='Détail'!P17/1000000 -> 387.64197 | R5: ='Détail'!P26/1000000 -> 376.82264 | S5: ='Détail'!P35/1000000 -> 398.33907 | T5: ='Détail'!P44/1000000 -> 386.48654 | U5: ='Détail'!P53/1000000 -> 387.96252 | V5: ='Détail'!P62/1000000 -> 408.05763 | W5: ='Détail'!P71/1000000 -> 374.28789 | X5: ='Détail'!P80/1000000 -> 396.99127 | Y5: ='Détail'!P89/1000000 -> 435.48415 | Z5: ='Détail'!P98/1000000 -> 420.70802 | AA5: ='Détail'!P107/1000000 -> 438.23525 | AB5: ='Détail'!P116/1000000 -> 429.82499
B6: % produit brut des jeux réalisé en points de vente | AA6: 84.6 | AB6: 81.4
B7: % produit brut des jeux réalisé sur la plateforme en ligne | AA7: 15.4 | AB7: =100-AB6 -> 18.6
B8: Bénéfice (milions) | G8: 172 | H8: 178.4 | I8: 188.5 | J8: 174.2 | K8: 183.2 | L8: 190.7 | M8: 198.7 | N8: 203.3 | O8: 203 | P8: 206 | Q8: 209.9 | R8: 209.5 | S8: 216.8 | T8: 216.2 | U8: 216.4 | V8: 224.3 | W8: 224.7 | X8: 235 | Y8: 243.4 | Z8: 243.7 | AA8: 258.23616 | AB8: 252.00529
B10: Commission pour les points de vente (milions) | O10: 68.120081 | P10: 69.596211 | Q10: 71.874502 | R10: 70.463545 | S10: 74.5 | T10: 71.6 | U10: 71.883425 | V10: 75.876415 | W10: 70.078282 | X10: 75.00421 | Y10: 80.909395 | Z10: 79.966479 | AA10: 79.386684 | AB10: 79.196622
B11: cafés et restaurants (nombre) | AA11: 734 | AB11: 707
B12: kiosques (nombre) | AA12: 739 | AB12: 733
B13: commerces (nombre) | AA13: 898 | AB13: 902
B14: total (nombre) | P14: 2651 | Q14: 2651 | R14: 2651 | S14: 2601 | T14: 2601 | U14: 2501 | V14: 2451 | W14: 2400 | X14: 2400 | Y14: 2400 | Z14: 2359 | AA14: 2371 | AB14: 2342
B15: Commission moyenne | P15: =P10*1000000/P14 -> 26252.814 | Q15: =Q10*1000000/Q14 -> 27112.223 | R15: =R10*1000000/R14 -> 26579.987 | S15: =S10*1000000/S14 -> 28642.83 | T15: =T10*1000000/T14 -> 27527.874 | U15: =U10*1000000/U14 -> 28741.873 | V15: =V10*1000000/V14 -> 30957.33 | W15: =W10*1000000/W14 -> 29199.284 | ... AB15: =AB10*1000000/AB14 -> 33815.808
B17: Rémunération de la Direction (milions) | W17: 2.24965 | X17: 2.274249 | Y17: 2.37152 | Z17: 2.312064 | AA17: 2.287502 | AB17: 2.241173
B18: EPT Direction | W18: 9.7 | X18: 9.8 | Y18: 9.7 | Z18: 9.2 | AA18: 9.2 | AB18: 8.9
B19: Salaire moyen mensuel direction | W19: =((W17*1000000)/W18)/13 -> 17840.206 | X19: =((X17*1000000)/X18)/13 -> 17851.248 | Y19: =((Y17*1000000)/Y18)/13 -> 18806.661 | Z19: =((Z17*1000000)/Z18)/13 -> 19331.639 | AA19: =((AA17*1000000)/AA18)/13 -> 19126.271 | AB19: =((AB17*1000000)/AB18)/13 -> 19370.553
B20: Marketing, publicité et communication (milions) | O20: 16.336196 | P20: 15.230183 | Q20: 15.23539 | R20: 13.817968 | S20: 13.742552 | T20: 14.041487 | U20: 14.141136 | V20: 13.411041 | W20: 11.219172 | X20: 11.374329 | Y20: 13.264486 | Z20: 13.00049 | AA20: 15.354708 | AB20: 13.925272
B22: Fondation suisse pour lencouragement du sport (FSES) - en millions | P22: 6.481835 | Q22: 10.30562 | R22: 6.592762 | S22: 10.650175 | T22: 10.63213 | U22: 10.652251 | V22: 11.051532 | W22: 11.082441 | X22: 11.599846 | Y22: 19.507412 | Z22: 19.519996 | AA22: 19.567627 | AB22: 19.608735
B23: Fédération suisse de courses de chevaux (FSC) | P23: 3.742702 | Q23: 3.832166 | R23: 3.829008 | S23: 3.752897 | T23: 3.573387 | U23: 3.387602 | V23: 3.313814 | W23: 3.030524 | X23: 3.043011 | Y23: 3.434566 | Z23: 3.420448 | AA23: 3.2342 | AB23: 2.870533
B25: Prévention du jeu excessif (milions) | P25: 1.888676 | Q25: 1.93821 | R25: 1.884113 | S25: 1.99 | T25: 1.932433 | U25: 1.939813 | V25: 2.040288 | W25: 1.87 | X25: 1.984956 | Y25: 2.177421 | Z25: 2.10354 | AA25: 2.191176 | AB25: 2.149125
B26: Joueurs en ligne | AA26: 174000 | AB26: 180000
B27: Contrôles des mesures de protection des joueuses et joueurs via des clients mystères dans les points de vente (nombre) | W27: 1715 | X27: 1266 | Y27: 2838 | Z27: 2831 | AA27: 2944 | AB27: 2959
A29: Swisslos | B29: Produit brut des jeux (milions) Bruttospielertrag | F29: 421 | G29: 489 | H29: 548 | I29: 582 | J29: 532 | K29: 530 | L29: 528.2244 | M29: 504.4281 | N29: 533.53136 | O29: 532.23901 | P29: 533.59183 | Q29: 568.33109 | R29: 518.56345 | S29: 598.73917 | T29: 553.46184 | U29: 555.39982 | V29: 594.73646 | W29: 620.02534 | X29: 699.49323 | Y29: 736.5424 | Z29: 738.15311 | AA29: 812.10699
B30: Prévention du jeu excessif (milions) Spielsuchtabgabe | P30: 2.684662 | Q30: 2.857357 | R30: 2.582677 | S30: 2.981379 | T30: 2.770326 | U30: 2.764488 | V30: 2.977186 | W30: 3.080985 | X30: 3.482176 | Y30: 3.674887 | Z30: 4.050498 | AA30: 3.683054
B31: Auszahlung an die Kantone | L31: 325.51389 | M31: 316.83569 | N31: 327.118 | O31: 325.95419 | P31: 336.97984 | Q31: 359.79858 | R31: 327.66866 | S31: 368.61025 | T31: 339.39147 | U31: 331.99248 | V31: 362.3228 | W31: 383.02558 | X31: 437.84184 | Y31: 434.23708 | Z31: 455.37004 | AA31: 540.05376
A33: CFMJ | B33: Produit brut des jeux (milions) - Casino A | L33: 553.53386 | M33: 524.15143 | N33: 494.5525 | O33: 451.21275 | P33: 449.56098 | Q33: 426.20628 | R33: 408.84793 | S33: 412.68357 | T33: 410.79168 | U33: 426.38237 | V33: 448.96273 | W33: 284.5886 | X33: 246.07185 | Y33: 375.12229 | Z33: 365.34936 | AA33: 341.07585
B34: Produit brut des jeux (milions) - Casino B | L34: 382.78364 | M34: 344.58586 | N34: 330.23716 | O34: 306.31234 | P34: 296.6069 | Q34: 283.60563 | R34: 273.31302 | S34: 277.04637 | T34: 270.01875 | U34: 277.2167 | V34: 293.49191 | W34: 167.37776 | X34: 159.72614 | Y34: 254.44867 | Z34: 258.50741 | AA34: 246.45555
B35: Produit brut des jeux (milions) - Total | C35: =if(C33+C34=0,"",C33+C34) | D35: =if(D33+D34=0,"",D33+D34) | E35: =if(E33+E34=0,"",E33+E34) | F35: =if(F33+F34=0,"",F33+F34) | G35: =if(G33+G34=0,"",G33+G34) | H35: =if(H33+H34=0,"",H33+H34) | I35: =if(I33+I34=0,"",I33+I34) | J35: =if(J33+J34=0,"",J33+J34) | ... AA35: =if(AA33+AA34=0,"",AA33+AA34) -> 587.5314
B36: Produit brut des jeux (milions) - Offre en ligne | V36: 23.493714 | W36: 186.81397 | X36: 234.46186 | Y36: 250.05615 | Z36: 285.70665 | AA36: 309.94731
A37: CFMJ | B37: Produit brut des jeux (milions) - FULL | C37: =if(C33+C34+C36=0,"",C33+C34+C36) | D37: =if(D33+D34+D36=0,"",D33+D34+D36) | E37: =if(E33+E34+E36=0,"",E33+E34+E36) | F37: =if(F33+F34+F36=0,"",F33+F34+F36) | G37: =if(G33+G34+G36=0,"",G33+G34+G36) | H37: =if(H33+H34+H36=0,"",H33+H34+H36) | I37: =if(I33+I34+I36=0,"",I33+I34+I36) | J37: =if(J33+J34+J36=0,"",J33+J34+J36) | ... AA37: =if(AA33+AA34+AA36=0,"",AA33+AA34+AA36) -> 897.47871
B39: Impôt sur les maisons de jeu en francs (milions) - Casino A | L39: 296.26155 | M39: 293.09251 | N39: 271.04802 | O39: 237.91769 | P39: 227.76663 | Q39: 212.43774 | R39: 202.53296 | S39: 204.98239 | T39: 204.51291 | U39: 213.66748 | V39: 227.30574 | W39: 129.42044 | X39: 108.90697 | Y39: 181.53583 | Z39: 175.83045 | AA39: 161.70456
B40: Impôt sur les maisons de jeu en francs (milions) - Casino B | L40: 182.72936 | M40: 156.70527 | N40: 148.20655 | O40: 135.70774 | P40: 128.78264 | Q40: 123.61452 | R40: 117.56099 | S40: 118.26818 | T40: 112.38743 | U40: 118.75848 | V40: 129.38104 | W40: 197.74937 | X40: 66.123699 | Y40: 112.2449 | Z40: 113.33211 | AA40: 107.05043
B41: Impôt sur les maisons de jeu en francs (milions) - Offre en ligne | V41: 7.459001 | W41: 78.049199 | X41: 99.680552 | Y41: 103.31838 | Z41: 120.11133 | AA41: 132.09206
B43: Taxes totales des maisons de jeu | C43: =if(C39+C40+C41=0,"",C39+C40+C41) | D43: =if(D39+D40+D41=0,"",D39+D40+D41) | E43: =if(E39+E40+E41=0,"",E39+E40+E41) | F43: =if(F39+F40+F41=0,"",F39+F40+F41) | G43: =if(G39+G40+G41=0,"",G39+G40+G41) | H43: =if(H39+H40+H41=0,"",H39+H40+H41) | I43: =if(I39+I40+I41=0,"",I39+I40+I41) | J43: =if(J39+J40+J41=0,"",J39+J40+J41) | ... AA43: =if(AA39+AA40+AA41=0,"",AA39+AA40+AA41) -> 400.84705
B45: Charges de transfert en faveur de lAVS | N45: 414.88173 | O45: 381.09624 | P45: 376.05386 | Q45: 329.35523 | R45: 307.71177 | S45: 285.32697 | T45: 271.56404 | U45: 273.6466 | V45: 272.26578 | W45: 274.19722 | X45: 305.2 | Y45: 269.04942 | Z45: 342.25131 | AA45: 325.92381

Sheet Détail
A1: Année | B1: Poste | C1: Libellé | D1: VAUD | F1: FRIBOURG | H1: VALAIS | J1: NEUCHÂTEL | L1: GENÈVE | N1: JURA | P1: TOTAL | Q1: Intercantonal | R1: Swisslos | S1: Culture | T1: Santé et handicap | U1: Jeunesse et éducation | V1: Action sociale et personnes âgées | W1: Sport | X1: Promotion, tourisme et développement | Y1: Environnement | Z1: Conservation du patrimoine | AA1: Formation et recherche
A2: 2013 | B2: Répartition | C2: Répartiton | D2: 33217743 | E2: =D2/(D2+H2+J2+L2+N2) -> 0.33493749 | F2: 16904793 | G2: =F2/(D2+F2+H2+J2+L2+N2) -> 0.14562961 | H2: 23832371 | I2: =H2/(D2+F2+J2+L2+N2) -> 0.25835005 | J2: 13286650 | K2: =J2/(D2+F2+H2+J2+L2+N2) -> 0.11446042 | L2: 22938216 | M2: =L2/(D2+F2+H2+J2+L2+N2) -> 0.1976057 | N2: 5900967 | O2: =N2/(D2+F2+H2+J2+L2+N2) -> 0.050835022 | P2: =SUM(D2:N2)+Q2 -> 1.3009274e+08 | Q2: 14012000 | S2: 58129001 | T2: 10098621 | U2: 11407769 | V2: 17927484 | W2: 34334787 | X2: 11009731 | Y2: 2874500 | Z2: 13903934 | AA2: 4741700
A3: 2013 | B3: Vente.1 | C3: Billets Instantanés | D3: 37786290 | E3: =D3/(D3+H3+J3+L3+N3) -> 0.4248003 | F3: 9674862 | G3: =F3/(D3+F3+H3+J3+L3+N3) -> 0.098096887 | H3: 21542305 | I3: =H3/(D3+F3+J3+L3+N3) -> 0.27946797 | J3: 10590107 | K3: =J3/(D3+F3+H3+J3+L3+N3) -> 0.10737688 | L3: 14476400 | M3: =L3/(D3+F3+H3+J3+L3+N3) -> 0.1467814 | N3: 4555612 | O3: =N3/(D3+F3+H3+J3+L3+N3) -> 0.04619098 | P3: =SUM(D3:N3) -> 98625577
A4: 2013 | B4: Vente.2 | C4: Jeux de tirages | D4: 56697217 | E4: =D4/(D4+H4+J4+L4+N4) -> 0.43780109 | F4: 18721542 | G4: =F4/(D4+F4+H4+J4+L4+N4) -> 0.12630399 | H4: 30090248 | I4: =H4/(D4+F4+J4+L4+N4) -> 0.25470896 | J4: 12408056 | K4: =J4/(D4+F4+H4+J4+L4+N4) -> 0.083710358 | L4: 25299785 | M4: =L4/(D4+F4+H4+J4+L4+N4) -> 0.17068379 | N4: 5009206 | O4: =N4/(D4+F4+H4+J4+L4+N4) -> 0.033794369 | P4: =SUM(D4:N4) -> 1.4822606e+08
A5: 2013 | B5: Vente.3 | C5: Paris sportifs | D5: 1695500 | E5: =D5/(D5+H5+J5+L5+N5) -> 0.42493149 | F5: 471569 | G5: =F5/(D5+F5+H5+J5+L5+N5) -> 0.10569447 | H5: 906958 | I5: =H5/(D5+F5+J5+L5+N5) -> 0.25514577 | J5: 423984 | K5: =J5/(D5+F5+H5+J5+L5+N5) -> 0.095029075 | L5: 855890 | M5: =L5/(D5+F5+H5+J5+L5+N5) -> 0.19183374 | N5: 107723 | O5: =N5/(D5+F5+H5+J5+L5+N5) -> 0.024144347 | P5: =SUM(D5:N5) -> 4461625.1
A6: 2013 | B6: Vente.4 | C6: Loterie électronique | D6: 35547603 | E6: =D6/(D6+H6+J6+L6+N6) -> 0.40509504 | F6: 5728975 | G6: =F6/(D6+F6+H6+J6+L6+N6) -> 0.06128541 | H6: 17407418 | I6: =H6/(D6+F6+J6+L6+N6) -> 0.22882571 | J6: 8709996 | K6: =J6/(D6+F6+H6+J6+L6+N6) -> 0.093174726 | L6: 22977976 | M6: =L6/(D6+F6+H6+J6+L6+N6) -> 0.24580569 | N6: 3108275 | O6: =N6/(D6+F6+H6+J6+L6+N6) -> 0.033250609 | P6: =SUM(D6:N6) -> 93480244
A7: 2013 | B7: Vente.5 | C7: PMUR | D7: 13701626 | E7: =D7/(D7+H7+J7+L7+N7) -> 0.43962016 | F7: 1774790 | G7: =F7/(D7+F7+H7+J7+L7+N7) -> 0.053876607 | H7: 4744389 | I7: =H7/(D7+F7+J7+L7+N7) -> 0.16825646 | J7: 4066692 | K7: =J7/(D7+F7+H7+J7+L7+N7) -> 0.12345098 | L7: 6846983 | M7: =L7/(D7+F7+H7+J7+L7+N7) -> 0.20785119 | N7: 1807275 | O7: =N7/(D7+F7+H7+J7+L7+N7) -> 0.054862742 | P7: =SUM(D7:N7) -> 32941756
A8: 2013 | B8: Vente.6 | C8: Total | D8: =SUM(D3:D7) -> 145428236 | E8: =D8/(D8+H8+J8+L8+N8) -> 0.42602162 | F8: =SUM(F3:F7) -> 36371738 | G8: =F8/(D8+F8+H8+J8+L8+N8) -> 0.096288969 | H8: =SUM(H3:H7) -> 74691318 | I8: =H8/(D8+F8+J8+L8+N8) -> 0.24647026 | J8: =SUM(J3:J7) -> 36198835 | K8: =J8/(D8+F8+H8+J8+L8+N8) -> 0.095831233 | L8: =SUM(L3:L7) -> 70457034 | M8: =L8/(D8+F8+H8+J8+L8+N8) -> 0.18652491 | N8: =SUM(N3:N7) -> 14588091 | O8: =N8/(D8+F8+H8+J8+L8+N8) -> 0.038619882 | P8: =SUM(P3:P7) -> 3.7773526e+08 | R8: =Total!P29*1000000 -> 533591829
A9: 2013 | B9: Vente.7 | C9: Point de vente | D9: 968 | E9: =D9/(D9+H9+J9+L9+N9) -> 0.41456103 | F9: 315 | G9: =F9/(D9+F9+H9+J9+L9+N9) -> 0.11886792 | H9: 492 | I9: =H9/(D9+F9+J9+L9+N9) -> 0.22798888 | J9: 272 | K9: =J9/(D9+F9+H9+J9+L9+N9) -> 0.10264151 | L9: 440 | M9: =L9/(D9+F9+H9+J9+L9+N9) -> 0.16603774 | N9: 163 | O9: =N9/(D9+F9+H9+J9+L9+N9) -> 0.061509434 | P9: =SUM(D9:N9) -> 2651.0301
A10: 2013 | B10: Vente.8 | C10: Population | D10: 734356 | E10: =D10/(D10+H10+J10+L10+N10) -> 0.41613999 | F10: 291395 | G10: =F10/(D10+F10+H10+J10+L10+N10) -> 0.14172357 | H10: 321732 | I10: =H10/(D10+F10+J10+L10+N10) -> 0.18550602 | J10: 174554 | K10: =J10/(D10+F10+H10+J10+L10+N10) -> 0.084896502 | L10: 463101 | M10: =L10/(D10+F10+H10+J10+L10+N10) -> 0.22523491 | N10: 70942 | O10: =N10/(D10+F10+H10+J10+L10+N10) -> 0.034503521 | P10: =SUM(D10:N10) -> 2056081.1
A11: 2014 | B11: Répartition | C11: Répartiton | D11: 36880059 | E11: =D11/(D11+H11+J11+L11+N11) -> 0.3424337 | F11: 14672240 | G11: =F11/(D11+F11+H11+J11+L11+N11) -> 0.11989858 | H11: 26149635 | I11: =H11/(D11+F11+J11+L11+N11) -> 0.27176229 | J11: 13549800 | K11: =J11/(D11+F11+H11+J11+L11+N11) -> 0.11072623 | L11: 25764723 | M11: =L11/(D11+F11+H11+J11+L11+N11) -> 0.21054411 | N11: 5355635 | O11: =N11/(D11+F11+H11+J11+L11+N11) -> 0.043765167 | P11: =SUM(D11:N11)+Q11 -> 1.3822674e+08 | Q11: 15854650 | S11: 62505562 | T11: 8559152 | U11: 12703848 | V11: 16892950 | X11: 11969835 | Y11: 2972500 | Z11: 14433704 | AA11: 8189191
A12: 2014 | B12: Vente.1 | C12: Billets Instantanés | D12: 39695036 | E12: =D12/(D12+H12+J12+L12+N12) -> 0.43153559 | F12: 10245764 | G12: =F12/(D12+F12+H12+J12+L12+N12) -> 0.10022139 | H12: 22159564 | I12: =H12/(D12+F12+J12+L12+N12) -> 0.27674637 | J12: 10613518 | K12: =J12/(D12+F12+H12+J12+L12+N12) -> 0.10381867 | L12: 14999555 | M12: =L12/(D12+F12+H12+J12+L12+N12) -> 0.14672174 | N12: 4517870 | O12: =N12/(D12+F12+H12+J12+L12+N12) -> 0.044192627 | P12: =SUM(D12:N12) -> 1.0223131e+08
A13: 2014 | B13: Vente.2 | C13: Jeux de tirages | D13: 58895648 | E13: =D13/(D13+H13+J13+L13+N13) -> 0.43294965 | F13: 19906298 | G13: =F13/(D13+F13+H13+J13+L13+N13) -> 0.12765375 | H13: 31719247 | I13: =H13/(D13+F13+J13+L13+N13) -> 0.25534625 | J13: 12468092 | K13: =J13/(D13+F13+H13+J13+L13+N13) -> 0.079954531 | L13: 27807385 | M13: =L13/(D13+F13+H13+J13+L13+N13) -> 0.1783213 | N13: 5143110 | O13: =N13/(D13+F13+H13+J13+L13+N13) -> 0.032981386 | P13: =SUM(D13:N13) -> 1.5593978e+08
A14: 2014 | B14: Vente.3 | C14: Paris sportifs | D14: 2012567 | E14: =D14/(D14+H14+J14+L14+N14) -> 0.38609709 | F14: 522809 | G14: =F14/(D14+F14+H14+J14+L14+N14) -> 0.091154726 | H14: 1032313 | I14: =H14/(D14+F14+J14+L14+N14) -> 0.2194968 | J14: 584241 | K14: =J14/(D14+F14+H14+J14+L14+N14) -> 0.10186575 | L14: 1474613 | M14: =L14/(D14+F14+H14+J14+L14+N14) -> 0.25710717 | N14: 108859 | O14: =N14/(D14+F14+H14+J14+L14+N14) -> 0.018980187 | P14: =SUM(D14:N14) -> 5735403.1
A15: 2014 | B15: Vente.4 | C15: Loterie électronique | D15: 34956508 | E15: =D15/(D15+H15+J15+L15+N15) -> 0.41573778 | F15: 6107242 | G15: =F15/(D15+F15+H15+J15+L15+N15) -> 0.067715058 | H15: 16137593 | I15: =H15/(D15+F15+J15+L15+N15) -> 0.21792034 | J15: 8472548 | K15: =J15/(D15+F15+H15+J15+L15+N15) -> 0.09394078 | L15: 21510247 | M15: =L15/(D15+F15+H15+J15+L15+N15) -> 0.23849843 | N15: 3006171 | O15: =N15/(D15+F15+H15+J15+L15+N15) -> 0.033331419 | P15: =SUM(D15:N15) -> 90190310
A16: 2014 | B16: Vente.5 | C16: PMUR | D16: 13642064 | E16: =D16/(D16+H16+J16+L16+N16) -> 0.43082784 | F16: 1880398 | G16: =F16/(D16+F16+H16+J16+L16+N16) -> 0.056055705 | H16: 4199916 | I16: =H16/(D16+F16+J16+L16+N16) -> 0.14312081 | J16: 3761548 | K16: =J16/(D16+F16+H16+J16+L16+N16) -> 0.11213383 | L16: 8267234 | M16: =L16/(D16+F16+H16+J16+L16+N16) -> 0.24645082 | N16: 1794007 | O16: =N16/(D16+F16+H16+J16+L16+N16) -> 0.053480342 | P16: =SUM(D16:N16) -> 33545168
A17: 2014 | B17: Vente.6 | C17: Total | D17: =SUM(D12:D16) -> 149201823 | E17: =D17/(D17+H17+J17+L17+N17) -> 0.42753756 | F17: =SUM(F12:F16) -> 38662511 | G17: =F17/(D17+F17+H17+J17+L17+N17) -> 0.099737682 | H17: =SUM(H12:H16) -> 75248633 | I17: =H17/(D17+F17+J17+L17+N17) -> 0.24087785 | J17: =SUM(J12:J16) -> 35899947 | K17: =J17/(D17+F17+H17+J17+L17+N17) -> 0.092611095 | L17: =SUM(L12:L16) -> 74059034 | M17: =L17/(D17+F17+H17+J17+L17+N17) -> 0.19105009 | N17: =SUM(N12:N16) -> 14570017 | O17: =N17/(D17+F17+H17+J17+L17+N17) -> 0.037586274 | P17: =SUM(P12:P16) -> 3.8764197e+08 | R17: =Total!Q29*1000000 -> 568331094
A18: 2014 | B18: Vente.7 | C18: Point de vente | D18: 983 | E18: =D18/(D18+H18+J18+L18+N18) -> 0.41972673 | F18: 308 | G18: =F18/(D18+F18+H18+J18+L18+N18) -> 0.11622642 | H18: 504 | I18: =H18/(D18+F18+J18+L18+N18) -> 0.23485555 | J18: 265 | K18: =J18/(D18+F18+H18+J18+L18+N18) -> 0.1 | L18: 433 | M18: =L18/(D18+F18+H18+J18+L18+N18) -> 0.16339623 | N18: 157 | O18: =N18/(D18+F18+H18+J18+L18+N18) -> 0.059245283 | P18: =SUM(D18:N18) -> 2651.0342
A19: 2014 | B19: Vente.8 | C19: Population | D19: 749373 | E19: =D19/(D19+H19+J19+L19+N19) -> 0.41772071 | F19: 297622 | G19: =F19/(D19+F19+H19+J19+L19+N19) -> 0.14229537 | H19: 327011 | I19: =H19/(D19+F19+J19+L19+N19) -> 0.18532071 | J19: 176402 | K19: =J19/(D19+F19+H19+J19+L19+N19) -> 0.084339152 | L19: 469433 | M19: =L19/(D19+F19+H19+J19+L19+N19) -> 0.22443953 | N19: 71738 | O19: =N19/(D19+F19+H19+J19+L19+N19) -> 0.034298489 | P19: =SUM(D19:N19) -> 2091580.1
A20: 2015 | B20: Répartition | C20: Répartiton | D20: 34153502 | E20: =D20/(D20+H20+J20+L20+N20) -> 0.31686526 | F20: 14478414 | G20: =F20/(D20+F20+H20+J20+L20+N20) -> 0.11841929 | H20: 23251870 | I20: =H20/(D20+F20+J20+L20+N20) -> 0.23483865 | J20: 12954500 | K20: =J20/(D20+F20+H20+J20+L20+N20) -> 0.10595516 | L20: 32285500 | M20: =L20/(D20+F20+H20+J20+L20+N20) -> 0.26406387 | N20: 5140195 | O20: =N20/(D20+F20+H20+J20+L20+N20) -> 0.042041777 | P20: =SUM(D20:N20)+Q20 -> 135392982 | Q20: 13129000 | S20: 62417400 | T20: 15413320 | U20: 12284385 | V20: 19371167 | W20: 34284209 | X20: 8615900 | Y20: 1782500 | Z20: 11910114 | AA20: 2363500
A21: 2015 | B21: Vente.1 | C21: Billets Instantanés | D21: 40763211 | E21: =D21/(D21+H21+J21+L21+N21) -> 0.43136412 | F21: 10648139 | G21: =F21/(D21+F21+H21+J21+L21+N21) -> 0.10126953 | H21: 22447054 | I21: =H21/(D21+F21+J21+L21+N21) -> 0.27142925 | J21: 11078348 | K21: =J21/(D21+F21+H21+J21+L21+N21) -> 0.10536105 | L21: 15580462 | M21: =L21/(D21+F21+H21+J21+L21+N21) -> 0.14817858 | N21: 4629305 | O21: =N21/(D21+F21+H21+J21+L21+N21) -> 0.044027183 | P21: =SUM(D21:N21) -> 1.0514652e+08
A22: 2015 | B22: Vente.2 | C22: Jeux de tirages | D22: 53815199 | E22: =D22/(D22+H22+J22+L22+N22) -> 0.43139061 | F22: 18525390 | G22: =F22/(D22+F22+H22+J22+L22+N22) -> 0.12930081 | H22: 29101367 | I22: =H22/(D22+F22+J22+L22+N22) -> 0.25489009 | J22: 11488057 | K22: =J22/(D22+F22+H22+J22+L22+N22) -> 0.080182659 | L22: 25335412 | M22: =L22/(D22+F22+H22+J22+L22+N22) -> 0.1768324 | N22: 5008159 | O22: =N22/(D22+F22+H22+J22+L22+N22) -> 0.034955215 | P22: =SUM(D22:N22) -> 1.4327359e+08
A23: 2015 | B23: Vente.3 | C23: Paris sportifs | D23: 1968012 | E23: =D23/(D23+H23+J23+L23+N23) -> 0.36910927 | F23: 755147 | G23: =F23/(D23+F23+H23+J23+L23+N23) -> 0.12406032 | H23: 1057744 | I23: =H23/(D23+F23+J23+L23+N23) -> 0.21032095 | J23: 531674 | K23: =J23/(D23+F23+H23+J23+L23+N23) -> 0.087346766 | L23: 1635037 | M23: =L23/(D23+F23+H23+J23+L23+N23) -> 0.26861422 | N23: 139320 | O23: =N23/(D23+F23+H23+J23+L23+N23) -> 0.02288837 | P23: =SUM(D23:N23) -> 6086935.1
A24: 2015 | B24: Vente.4 | C24: Loterie électronique | D24: 34591001 | E24: =D24/(D24+H24+J24+L24+N24) -> 0.41730399 | F24: 6007804 | G24: =F24/(D24+F24+H24+J24+L24+N24) -> 0.06757979 | H24: 15763731 | I24: =H24/(D24+F24+J24+L24+N24) -> 0.21554089 | J24: 8277465 | K24: =J24/(D24+F24+H24+J24+L24+N24) -> 0.093110452 | L24: 21224516 | M24: =L24/(D24+F24+H24+J24+L24+N24) -> 0.23874752 | N24: 3034901 | O24: =N24/(D24+F24+H24+J24+L24+N24) -> 0.034138592 | P24: =SUM(D24:N24) -> 88899419
A25: 2015 | B25: Vente.5 | C25: PMUR | D25: 13168548 | E25: =D25/(D25+H25+J25+L25+N25) -> 0.41829797 | F25: 1934921 | G25: =F25/(D25+F25+H25+J25+L25+N25) -> 0.057903711 | H25: 4066547 | I25: =H25/(D25+F25+J25+L25+N25) -> 0.13855528 | J25: 3509440 | K25: =J25/(D25+F25+H25+J25+L25+N25) -> 0.10502217 | L25: 9076286 | M25: =L25/(D25+F25+H25+J25+L25+N25) -> 0.27161349 | N25: 1660441 | O25: =N25/(D25+F25+H25+J25+L25+N25) -> 0.049689727 | P25: =SUM(D25:N25) -> 33416184
A26: 2015 | B26: Vente.6 | C26: Total | D26: =SUM(D21:D25) -> 144305971 | E26: =D26/(D26+H26+J26+L26+N26) -> 0.42574257 | F26: =SUM(F21:F25) -> 37871401 | G26: =F26/(D26+F26+H26+J26+L26+N26) -> 0.10050193 | H26: =SUM(H21:H25) -> 72436443 | I26: =H26/(D26+F26+J26+L26+N26) -> 0.23797545 | J26: =SUM(J21:J25) -> 34884984 | K26: =J26/(D26+F26+H26+J26+L26+N26) -> 0.092576667 | L26: =SUM(L21:L25) -> 72851713 | M26: =L26/(D26+F26+H26+J26+L26+N26) -> 0.19333157 | N26: =SUM(N21:N25) -> 14472126 | O26: =N26/(D26+F26+H26+J26+L26+N26) -> 0.03840567 | P26: =SUM(P21:P25) -> 3.7682264e+08 | R26: =Total!R29*1000000 -> 518563445
A27: 2015 | B27: Vente.7 | C27: Point de vente | D27: 983 | E27: =D27/(D27+H27+J27+L27+N27) -> 0.41972673 | F27: 308 | G27: =F27/(D27+F27+H27+J27+L27+N27) -> 0.11622642 | H27: 504 | I27: =H27/(D27+F27+J27+L27+N27) -> 0.23485555 | J27: 265 | K27: =J27/(D27+F27+H27+J27+L27+N27) -> 0.1 | L27: 433 | M27: =L27/(D27+F27+H27+J27+L27+N27) -> 0.16339623 | N27: 157 | O27: =N27/(D27+F27+H27+J27+L27+N27) -> 0.059245283 | P27: =SUM(D27:N27) -> 2651.0342
A28: 2015 | B28: Vente.8 | C28: Population | D28: 761446 | E28: =D28/(D28+H28+J28+L28+N28) -> 0.41830085 | F28: 303377 | G28: =F28/(D28+F28+H28+J28+L28+N28) -> 0.1428525 | H28: 331763 | I28: =H28/(D28+F28+J28+L28+N28) -> 0.18514128 | J28: 177327 | K28: =J28/(D28+F28+H28+J28+L28+N28) -> 0.083498767 | L28: 477385 | M28: =L28/(D28+F28+H28+J28+L28+N28) -> 0.22478844 | N28: 72410 | O28: =N28/(D28+F28+H28+J28+L28+N28) -> 0.034096025 | P28: =SUM(D28:N28) -> 2123709.1
A29: 2016 | B29: Répartition | C29: Répartiton | D29: 34846396 | E29: =D29/(D29+H29+J29+L29+N29) -> 0.3237332 | F29: 17316651 | G29: =F29/(D29+F29+H29+J29+L29+N29) -> 0.13858211 | H29: 25143905 | I29: =H29/(D29+F29+J29+L29+N29) -> 0.25191268 | J29: 13302310 | K29: =J29/(D29+F29+H29+J29+L29+N29) -> 0.10645604 | L29: 28579210 | M29: =L29/(D29+F29+H29+J29+L29+N29) -> 0.22871439 | N29: 5767420 | O29: =N29/(D29+F29+H29+J29+L29+N29) -> 0.046155647 | P29: =SUM(D29:N29)+Q29 -> 136853193 | Q29: 11897300 | S29: 66764794 | T29: 8716060 | U29: 12591383 | V29: 20110251 | W29: 35500584 | X29: 7000000 | Y29: 2337760 | Z29: 15390944 | AA29: 3942000
A30: 2016 | B30: Vente.1 | C30: Billets Instantanés | D30: 43254073 | E30: =D30/(D30+H30+J30+L30+N30) -> 0.43232558 | F30: 11488184 | G30: =F30/(D30+F30+H30+J30+L30+N30) -> 0.10299799 | H30: 23805549 | I30: =H30/(D30+F30+J30+L30+N30) -> 0.27134273 | J30: 11640310 | K30: =J30/(D30+F30+H30+J30+L30+N30) -> 0.10436188 | L30: 16619613 | M30: =L30/(D30+F30+H30+J30+L30+N30) -> 0.14900411 | N30: 4730220 | O30: =N30/(D30+F30+H30+J30+L30+N30) -> 0.042409064 | P30: =SUM(D30:N30) -> 1.1153795e+08
A31: 2016 | B31: Vente.2 | C31: Jeux de tirages | D31: 58413917 | E31: =D31/(D31+H31+J31+L31+N31) -> 0.42782883 | F31: 20620419 | G31: =F31/(D31+F31+H31+J31+L31+N31) -> 0.13120976 | H31: 32242070 | I31: =H31/(D31+F31+J31+L31+N31) -> 0.258114 | J31: 12316429 | K31: =J31/(D31+F31+H31+J31+L31+N31) -> 0.078370652 | L31: 27896991 | M31: =L31/(D31+F31+H31+J31+L31+N31) -> 0.17751131 | N31: 5666311 | O31: =N31/(D31+F31+H31+J31+L31+N31) -> 0.036055296 | P31: =SUM(D31:N31) -> 1.5715614e+08
A32: 2016 | B32: Vente.3 | C32: Paris sportifs | D32: 2388859 | E32: =D32/(D32+H32+J32+L32+N32) -> 0.37883652 | F32: 829119 | G32: =F32/(D32+F32+H32+J32+L32+N32) -> 0.11620616 | H32: 1262788 | I32: =H32/(D32+F32+J32+L32+N32) -> 0.21504846 | J32: 578160 | K32: =J32/(D32+F32+H32+J32+L32+N32) -> 0.081032704 | L32: 1917234 | M32: =L32/(D32+F32+H32+J32+L32+N32) -> 0.26871222 | N32: 158737 | O32: =N32/(D32+F32+H32+J32+L32+N32) -> 0.022247974 | P32: =SUM(D32:N32) -> 7134898.1
A33: 2016 | B33: Vente.4 | C33: Loterie électronique | D33: 35064098 | E33: =D33/(D33+H33+J33+L33+N33) -> 0.41939823 | F33: 6263815 | G33: =F33/(D33+F33+H33+J33+L33+N33) -> 0.069698968 | H33: 16084994 | I33: =H33/(D33+F33+J33+L33+N33) -> 0.21799946 | J33: 8040021 | K33: =J33/(D33+F33+H33+J33+L33+N33) -> 0.089463237 | L33: 21389589 | M33: =L33/(D33+F33+H33+J33+L33+N33) -> 0.23800707 | N33: 3027035 | O33: =N33/(D33+F33+H33+J33+L33+N33) -> 0.033682542 | P33: =SUM(D33:N33) -> 89869553
A34: 2016 | B34: Vente.5 | C34: PMUR | D34: 12690387 | E34: =D34/(D34+H34+J34+L34+N34) -> 0.4101798 | F34: 1701929 | G34: =F34/(D34+F34+H34+J34+L34+N34) -> 0.052141594 | H34: 4185934 | I34: =H34/(D34+F34+J34+L34+N34) -> 0.14710927 | J34: 3749776 | K34: =J34/(D34+F34+H34+J34+L34+N34) -> 0.114881 | L34: 8750460 | M34: =L34/(D34+F34+H34+J34+L34+N34) -> 0.26808576 | N34: 1562039 | O34: =N34/(D34+F34+H34+J34+L34+N34) -> 0.047855817 | P34: =SUM(D34:N34) -> 32640526
A35: 2016 | B35: Vente.6 | C35: Total | D35: =SUM(D30:D34) -> 151811334 | E35: =D35/(D35+H35+J35+L35+N35) -> 0.4247236 | F35: =SUM(F30:F34) -> 40903466 | G35: =F35/(D35+F35+H35+J35+L35+N35) -> 0.10268505 | H35: =SUM(H30:H34) -> 77581335 | I35: =H35/(D35+F35+J35+L35+N35) -> 0.24186895 | J35: =SUM(J30:J34) -> 36324696 | K35: =J35/(D35+F35+H35+J35+L35+N35) -> 0.091190394 | L35: =SUM(L30:L34) -> 76573887 | M35: =L35/(D35+F35+H35+J35+L35+N35) -> 0.19223294 | N35: =SUM(N30:N34) -> 15144342 | O35: =N35/(D35+F35+H35+J35+L35+N35) -> 0.038018722 | P35: =SUM(P30:P34) -> 3.9833907e+08 | R35: =Total!S29*1000000 -> 598739168
A36: 2016 | B36: Vente.7 | C36: Point de vente | D36: 962 | E36: =D36/(D36+H36+J36+L36+N36) -> 0.4184428 | F36: 301 | G36: =F36/(D36+F36+H36+J36+L36+N36) -> 0.11576923 | H36: 502 | I36: =H36/(D36+F36+J36+L36+N36) -> 0.2392755 | J36: 255 | K36: =J36/(D36+F36+H36+J36+L36+N36) -> 0.098076923 | L36: 429 | M36: =L36/(D36+F36+H36+J36+L36+N36) -> 0.165 | N36: 151 | O36: =N36/(D36+F36+H36+J36+L36+N36) -> 0.058076923 | P36: =SUM(D36:N36) -> 2601.0366
A37: 2016 | B37: Vente.8 | C37: Population | D37: 773407 | E37: =D37/(D37+H37+J37+L37+N37) -> 0.41925259 | F37: 307461 | G37: =F37/(D37+F37+H37+J37+L37+N37) -> 0.14285967 | H37: 335696 | I37: =H37/(D37+F37+J37+L37+N37) -> 0.18480446 | J37: 178107 | K37: =J37/(D37+F37+H37+J37+L37+N37) -> 0.082756208 | L37: 484736 | M37: =L37/(D37+F37+H37+J37+L37+N37) -> 0.22522929 | N37: 72782 | O37: =N37/(D37+F37+H37+J37+L37+N37) -> 0.033817662 | P37: =SUM(D37:N37) -> 2152190.1
A38: 2017 | B38: Répartition | C38: Répartiton | D38: 40437100 | E38: =D38/(D38+H38+J38+L38+N38) -> 0.3352218 | F38: 17156388 | G38: =F38/(D38+F38+H38+J38+L38+N38) -> 0.12451629 | H38: 27088102 | I38: =H38/(D38+F38+J38+L38+N38) -> 0.24470675 | J38: 14360550 | K38: =J38/(D38+F38+H38+J38+L38+N38) -> 0.10422488 | L38: 32102825 | M38: =L38/(D38+F38+H38+J38+L38+N38) -> 0.23299338 | N38: 6639316 | O38: =N38/(D38+F38+H38+J38+L38+N38) -> 0.048186309 | P38: =SUM(D38:N38)+Q38 -> 149148782 | Q38: 11364500 | S38: 64569860 | T38: 8750600 | U38: 15835213 | V38: 24953377 | W38: 35440433 | X38: 13225300 | Y38: 2933500 | Z38: 10862094 | AA38: 5308500
A39: 2017 | B39: Vente.1 | C39: Billets Instantanés | D39: 43189455 | E39: =D39/(D39+H39+J39+L39+N39) -> 0.43717502 | F39: 11547933 | G39: =F39/(D39+F39+H39+J39+L39+N39) -> 0.10465765 | H39: 23123106 | I39: =H39/(D39+F39+J39+L39+N39) -> 0.26512165 | J39: 11307647 | K39: =J39/(D39+F39+H39+J39+L39+N39) -> 0.10247997 | L39: 16591099 | M39: =L39/(D39+F39+H39+J39+L39+N39) -> 0.15036332 | N39: 4580831 | O39: =N39/(D39+F39+H39+J39+L39+N39) -> 0.041515571 | P39: =SUM(D39:N39) -> 1.1034007e+08
A40: 2017 | B40: Vente.2 | C40: Jeux de tirages | D40: 57395367 | E40: =D40/(D40+H40+J40+L40+N40) -> 0.42950607 | F40: 19735210 | G40: =F40/(D40+F40+H40+J40+L40+N40) -> 0.12868022 | H40: 30927732 | I40: =H40/(D40+F40+J40+L40+N40) -> 0.25259794 | J40: 11852157 | K40: =J40/(D40+F40+H40+J40+L40+N40) -> 0.077280058 | L40: 27987042 | M40: =L40/(D40+F40+H40+J40+L40+N40) -> 0.18248495 | N40: 5468798 | O40: =N40/(D40+F40+H40+J40+L40+N40) -> 0.035658406 | P40: =SUM(D40:N40) -> 1.5336631e+08
A41: 2017 | B41: Vente.3 | C41: Paris sportifs | D41: 2520957 | E41: =D41/(D41+H41+J41+L41+N41) -> 0.40050537 | F41: 721977 | G41: =F41/(D41+F41+H41+J41+L41+N41) -> 0.10289825 | H41: 1090335 | I41: =H41/(D41+F41+J41+L41+N41) -> 0.18398919 | J41: 641635 | K41: =J41/(D41+F41+H41+J41+L41+N41) -> 0.091447672 | L41: 1878482 | M41: =L41/(D41+F41+H41+J41+L41+N41) -> 0.26772668 | N41: 163031 | O41: =N41/(D41+F41+H41+J41+L41+N41) -> 0.023235649 | P41: =SUM(D41:N41) -> 7016418
A42: 2017 | B42: Vente.4 | C42: Loterie électronique | D42: 32935406 | E42: =D42/(D42+H42+J42+L42+N42) -> 0.42053017 | F42: 6260631 | G42: =F42/(D42+F42+H42+J42+L42+N42) -> 0.074020753 | H42: 14641372 | I42: =H42/(D42+F42+J42+L42+N42) -> 0.20934779 | J42: 7803757 | K42: =J42/(D42+F42+H42+J42+L42+N42) -> 0.092265455 | L42: 20282527 | M42: =L42/(D42+F42+H42+J42+L42+N42) -> 0.23980457 | N42: 2655709 | O42: =N42/(D42+F42+H42+J42+L42+N42) -> 0.031399004 | P42: =SUM(D42:N42) -> 84579403
A43: 2017 | B43: Vente.5 | C43: PMUR | D43: 12501876 | E43: =D43/(D43+H43+J43+L43+N43) -> 0.42186066 | F43: 1549256 | G43: =F43/(D43+F43+H43+J43+L43+N43) -> 0.049680577 | H43: 3778288 | I43: =H43/(D43+F43+J43+L43+N43) -> 0.13786327 | J43: 3448109 | K43: =J43/(D43+F43+H43+J43+L43+N43) -> 0.11057181 | L43: 8613822 | M43: =L43/(D43+F43+H43+J43+L43+N43) -> 0.27622268 | N43: 1292989 | O43: =N43/(D43+F43+H43+J43+L43+N43) -> 0.041462766 | P43: =SUM(D43:N43) -> 31184341
A44: 2017 | B44: Vente.6 | C44: Total | D44: =SUM(D39:D43) -> 148543061 | E44: =D44/(D44+H44+J44+L44+N44) -> 0.42848359 | F44: =SUM(F39:F43) -> 39815007 | G44: =F44/(D44+F44+H44+J44+L44+N44) -> 0.10301784 | H44: =SUM(H39:H43) -> 73560833 | I44: =H44/(D44+F44+J44+L44+N44) -> 0.23507444 | J44: =SUM(J39:J43) -> 35053305 | K44: =J44/(D44+F44+H44+J44+L44+N44) -> 0.090697351 | L44: =SUM(L39:L43) -> 75352972 | M44: =L44/(D44+F44+H44+J44+L44+N44) -> 0.1949692 | N44: =SUM(N39:N43) -> 14161358 | O44: =N44/(D44+F44+H44+J44+L44+N44) -> 0.036641271 | P44: =SUM(P39:P43) -> 3.8648654e+08 | R44: =Total!T29*1000000 -> 553461839
A45: 2017 | B45: Vente.7 | C45: Point de vente | D45: 962 | E45: =D45/(D45+H45+J45+L45+N45) -> 0.4184428 | F45: 301 | G45: =F45/(D45+F45+H45+J45+L45+N45) -> 0.11576923 | H45: 502 | I45: =H45/(D45+F45+J45+L45+N45) -> 0.2392755 | J45: 255 | K45: =J45/(D45+F45+H45+J45+L45+N45) -> 0.098076923 | L45: 429 | M45: =L45/(D45+F45+H45+J45+L45+N45) -> 0.165 | N45: 151 | O45: =N45/(D45+F45+H45+J45+L45+N45) -> 0.058076923 | P45: =SUM(D45:N45) -> 2601.0366
A46: 2017 | B46: Vente.8 | C46: Population | D46: 784822 | E46: =D46/(D46+H46+J46+L46+N46) -> 0.42076848 | F46: 311914 | G46: =F46/(D46+F46+H46+J46+L46+N46) -> 0.14326876 | H46: 339176 | I46: =H46/(D46+F46+J46+L46+N46) -> 0.18454049 | J46: 178567 | K46: =J46/(D46+F46+H46+J46+L46+N46) -> 0.082019636 | L46: 489524 | M46: =L46/(D46+F46+H46+J46+L46+N46) -> 0.22484883 | N46: 73122 | O46: =N46/(D46+F46+H46+J46+L46+N46) -> 0.033586496 | P46: =SUM(D46:N46) -> 2177126.1
A47: 2018 | B47: Répartition | C47: Répartiton | D47: 38632360 | E47: =D47/(D47+H47+J47+L47+N47) -> 0.28819863 | F47: 19944842 | G47: =F47/(D47+F47+H47+J47+L47+N47) -> 0.12951824 | H47: 33255111 | I47: =H47/(D47+F47+J47+L47+N47) -> 0.27543334 | J47: 15770200 | K47: =J47/(D47+F47+H47+J47+L47+N47) -> 0.10240886 | L47: 40630366 | M47: =L47/(D47+F47+H47+J47+L47+N47) -> 0.26384634 | N47: 5759651 | O47: =N47/(D47+F47+H47+J47+L47+N47) -> 0.037402145 | P47: =SUM(D47:N47)+Q47 -> 1.6470513e+08 | Q47: 10712600 | S47: 77594623 | T47: 11800560 | U47: 14401698 | V47: 17804145 | W47: 35507503 | X47: 12711500 | Y47: 3198500 | Z47: 17041784 | AA47: 7511000
A48: 2018 | B48: Vente.1 | C48: Billets Instantanés | D48: 43705543 | E48: =D48/(D48+H48+J48+L48+N48) -> 0.43787869 | F48: 12305099 | G48: =F48/(D48+F48+H48+J48+L48+N48) -> 0.10975222 | H48: 23159858 | I48: =H48/(D48+F48+J48+L48+N48) -> 0.26034823 | J48: 11689955 | K48: =J48/(D48+F48+H48+J48+L48+N48) -> 0.1042656 | L48: 16644319 | M48: =L48/(D48+F48+H48+J48+L48+N48) -> 0.14845479 | N48: 4612315 | O48: =N48/(D48+F48+H48+J48+L48+N48) -> 0.041138376 | P48: =SUM(D48:N48) -> 1.1211709e+08
A49: 2018 | B49: Vente.2 | C49: Jeux de tirages | D49: 55987132 | E49: =D49/(D49+H49+J49+L49+N49) -> 0.42665372 | F49: 19143239 | G49: =F49/(D49+F49+H49+J49+L49+N49) -> 0.12731006 | H49: 30239468 | I49: =H49/(D49+F49+J49+L49+N49) -> 0.25172791 | J49: 11764147 | K49: =J49/(D49+F49+H49+J49+L49+N49) -> 0.078236196 | L49: 27906608 | M49: =L49/(D49+F49+H49+J49+L49+N49) -> 0.1855899 | N49: 5326468 | O49: =N49/(D49+F49+H49+J49+L49+N49) -> 0.035423103 | P49: =SUM(D49:N49) -> 1.5036706e+08
A50: 2018 | B50: Vente.3 | C50: Paris sportifs | D50: 4471843 | E50: =D50/(D50+H50+J50+L50+N50) -> 0.3896728 | F50: 1294942 | G50: =F50/(D50+F50+H50+J50+L50+N50) -> 0.10139839 | H50: 2096855 | I50: =H50/(D50+F50+J50+L50+N50) -> 0.19644549 | J50: 914147 | K50: =J50/(D50+F50+H50+J50+L50+N50) -> 0.071580838 | L50: 3671657 | M50: =L50/(D50+F50+H50+J50+L50+N50) -> 0.28750331 | N50: 321390 | O50: =N50/(D50+F50+H50+J50+L50+N50) -> 0.025165937 | P50: =SUM(D50:N50) -> 12770835
A51: 2018 | B51: Vente.4 | C51: Loterie électronique | D51: 33005667 | E51: =D51/(D51+H51+J51+L51+N51) -> 0.42813177 | F51: 6135150 | G51: =F51/(D51+F51+H51+J51+L51+N51) -> 0.073715454 | H51: 14453867 | I51: =H51/(D51+F51+J51+L51+N51) -> 0.21016594 | J51: 7567150 | K51: =J51/(D51+F51+H51+J51+L51+N51) -> 0.090921314 | L51: 19612739 | M51: =L51/(D51+F51+H51+J51+L51+N51) -> 0.23565226 | N51: 2452887 | O51: =N51/(D51+F51+H51+J51+L51+N51) -> 0.029472088 | P51: =SUM(D51:N51) -> 83227461
A52: 2018 | B52: Vente.5 | C52: PMUR | D52: 11293874 | E52: =D52/(D52+H52+J52+L52+N52) -> 0.40460411 | F52: 1566671 | G52: =F52/(D52+F52+H52+J52+L52+N52) -> 0.053143404 | H52: 3778454 | I52: =H52/(D52+F52+J52+L52+N52) -> 0.14701234 | J52: 3360314 | K52: =J52/(D52+F52+H52+J52+L52+N52) -> 0.11398598 | L52: 8326455 | M52: =L52/(D52+F52+H52+J52+L52+N52) -> 0.28244358 | N52: 1154297 | O52: =N52/(D52+F52+H52+J52+L52+N52) -> 0.039155171 | P52: =SUM(D52:N52) -> 29480066
A53: 2018 | B53: Vente.6 | C53: Total | D53: =SUM(D48:D52) -> 148464059 | E53: =D53/(D53+H53+J53+L53+N53) -> 0.4272133 | F53: =SUM(F48:F52) -> 40445101 | G53: =F53/(D53+F53+H53+J53+L53+N53) -> 0.10425002 | H53: =SUM(H48:H52) -> 73728502 | I53: =H53/(D53+F53+J53+L53+N53) -> 0.23462929 | J53: =SUM(J48:J52) -> 35295713 | K53: =J53/(D53+F53+H53+J53+L53+N53) -> 0.090977123 | L53: =SUM(L48:L52) -> 76161778 | M53: =L53/(D53+F53+H53+J53+L53+N53) -> 0.19631221 | N53: =SUM(N48:N52) -> 13867357 | O53: =N53/(D53+F53+H53+J53+L53+N53) -> 0.035744065 | P53: =SUM(P48:P52) -> 3.8796252e+08 | R53: =Total!U29*1000000 -> 555399824
A54: 2018 | B54: Vente.7 | C54: Point de vente | D54: 942 | E54: =D54/(D54+H54+J54+L54+N54) -> 0.42663043 | F54: 292 | G54: =F54/(D54+F54+H54+J54+L54+N54) -> 0.1168 | H54: 466 | I54: =H54/(D54+F54+J54+L54+N54) -> 0.22910521 | J54: 244 | K54: =J54/(D54+F54+H54+J54+L54+N54) -> 0.0976 | L54: 420 | M54: =L54/(D54+F54+H54+J54+L54+N54) -> 0.168 | N54: 136 | O54: =N54/(D54+F54+H54+J54+L54+N54) -> 0.0544 | P54: =SUM(D54:N54) -> 2501.0381
A55: 2018 | B55: Vente.8 | C55: Population | D55: 793129 | E55: =D55/(D55+H55+J55+L55+N55) -> 0.42163155 | F55: 315074 | G55: =F55/(D55+F55+H55+J55+L55+N55) -> 0.14346528 | H55: 341463 | I55: =H55/(D55+F55+J55+L55+N55) -> 0.18410627 | J55: 177964 | K55: =J55/(D55+F55+H55+J55+L55+N55) -> 0.081033837 | L55: 495249 | M55: =L55/(D55+F55+H55+J55+L55+N55) -> 0.22550587 | N55: 73290 | O55: =N55/(D55+F55+H55+J55+L55+N55) -> 0.033371749 | P55: =SUM(D55:N55) -> 2196170.1
A56: 2019 | B56: Répartition | C56: Répartiton | D56: 41258170 | E56: =D56/(D56+H56+J56+L56+N56) -> 0.34848065 | F56: 19802308 | G56: =F56/(D56+F56+H56+J56+L56+N56) -> 0.1432907 | H56: 30277691 | I56: =H56/(D56+F56+J56+L56+N56) -> 0.28055927 | J56: 14023950 | K56: =J56/(D56+F56+H56+J56+L56+N56) -> 0.10147815 | L56: 27092160 | M56: =L56/(D56+F56+H56+J56+L56+N56) -> 0.19604051 | N56: 5742465 | O56: =N56/(D56+F56+H56+J56+L56+N56) -> 0.041552824 | P56: =SUM(D56:N56)+Q56 -> 1.5164595e+08 | Q56: 13449200 | S56: 73191631 | T56: 11904800 | U56: 17272678 | V56: 16718880 | W56: 36838440 | X56: 12415100 | Y56: 2767000 | Z56: 12226624 | AA56: 2503040
A57: 2019 | B57: Vente.1 | C57: Billets Instantanés | D57: 47486109 | E57: =D57/(D57+H57+J57+L57+N57) -> 0.43931461 | F57: 13786135 | G57: =F57/(D57+F57+H57+J57+L57+N57) -> 0.1131147 | H57: 24951674 | I57: =H57/(D57+F57+J57+L57+N57) -> 0.25743064 | J57: 12315837 | K57: =J57/(D57+F57+H57+J57+L57+N57) -> 0.10105096 | L57: 18399453 | M57: =L57/(D57+F57+H57+J57+L57+N57) -> 0.15096679 | N57: 4938277 | O57: =N57/(D57+F57+H57+J57+L57+N57) -> 0.04051837 | P57: =SUM(D57:N57) -> 1.2187749e+08
A58: 2019 | B58: Vente.2 | C58: Jeux de tirages | D58: 60279504 | E58: =D58/(D58+H58+J58+L58+N58) -> 0.42549345 | F58: 19852536 | G58: =F58/(D58+F58+H58+J58+L58+N58) -> 0.12290904 | H58: 32200708 | I58: =H58/(D58+F58+J58+L58+N58) -> 0.24899739 | J58: 12662287 | K58: =J58/(D58+F58+H58+J58+L58+N58) -> 0.07839349 | L58: 30762903 | M58: =L58/(D58+F58+H58+J58+L58+N58) -> 0.19045622 | N58: 5764237 | O58: =N58/(D58+F58+H58+J58+L58+N58) -> 0.03568697 | P58: =SUM(D58:N58) -> 1.6152218e+08
A59: 2019 | B59: Vente.3 | C59: Paris sportifs | D59: 8089397 | E59: =D59/(D59+H59+J59+L59+N59) -> 0.453359 | F59: 1953059 | G59: =F59/(D59+F59+H59+J59+L59+N59) -> 0.098657745 | H59: 2708429 | I59: =H59/(D59+F59+J59+L59+N59) -> 0.15850002 | J59: 1425115 | K59: =J59/(D59+F59+H59+J59+L59+N59) -> 0.071988932 | L59: 5154600 | M59: =L59/(D59+F59+H59+J59+L59+N59) -> 0.2603819 | N59: 465707 | O59: =N59/(D59+F59+H59+J59+L59+N59) -> 0.023524943 | P59: =SUM(D59:N59) -> 19796308
A60: 2019 | B60: Vente.4 | C60: Loterie électronique | D60: 30478084 | E60: =D60/(D60+H60+J60+L60+N60) -> 0.43392165 | F60: 5861432 | G60: =F60/(D60+F60+H60+J60+L60+N60) -> 0.077022646 | H60: 12642231 | I60: =H60/(D60+F60+J60+L60+N60) -> 0.19922239 | J60: 6807643 | K60: =J60/(D60+F60+H60+J60+L60+N60) -> 0.089456412 | L60: 17913628 | M60: =L60/(D60+F60+H60+J60+L60+N60) -> 0.23539555 | N60: 2397094 | O60: =N60/(D60+F60+H60+J60+L60+N60) -> 0.031499218 | P60: =SUM(D60:N60) -> 76100113
A61: 2019 | B61: Vente.5 | C61: PMUR | D61: 10732354 | E61: =D61/(D61+H61+J61+L61+N61) -> 0.39233477 | F61: 1406449 | G61: =F61/(D61+F61+H61+J61+L61+N61) -> 0.048900334 | H61: 3664306 | I61: =H61/(D61+F61+J61+L61+N61) -> 0.14600436 | J61: 3360920 | K61: =J61/(D61+F61+H61+J61+L61+N61) -> 0.11685465 | L61: 8576483 | M61: =L61/(D61+F61+H61+J61+L61+N61) -> 0.29819274 | N61: 1021030 | O61: =N61/(D61+F61+H61+J61+L61+N61) -> 0.035499835 | P61: =SUM(D61:N61) -> 28761543
A62: 2019 | B62: Vente.6 | C62: Total | D62: =SUM(D57:D61) -> 157065448 | E62: =D62/(D62+H62+J62+L62+N62) -> 0.43008298 | F62: =SUM(F57:F61) -> 42859611 | G62: =F62/(D62+F62+H62+J62+L62+N62) -> 0.10503323 | H62: =SUM(H57:H61) -> 76167348 | I62: =H62/(D62+F62+J62+L62+N62) -> 0.22949557 | J62: =SUM(J57:J61) -> 36571802 | K62: =J62/(D62+F62+H62+J62+L62+N62) -> 0.089624112 | L62: =SUM(L57:L61) -> 80807067 | M62: =L62/(D62+F62+H62+J62+L62+N62) -> 0.19802857 | N62: =SUM(N57:N61) -> 14586345 | O62: =N62/(D62+F62+H62+J62+L62+N62) -> 0.035745797 | P62: =SUM(P57:P61) -> 4.0805763e+08 | R62: =Total!V29*1000000 -> 594736460
A63: 2019 | B63: Vente.7 | C63: Point de vente | D63: 913 | E63: =D63/(D63+H63+J63+L63+N63) -> 0.42386258 | F63: 296 | G63: =F63/(D63+F63+H63+J63+L63+N63) -> 0.12081633 | H63: 444 | I63: =H63/(D63+F63+J63+L63+N63) -> 0.22133599 | J63: 238 | K63: =J63/(D63+F63+H63+J63+L63+N63) -> 0.097142857 | L63: 428 | M63: =L63/(D63+F63+H63+J63+L63+N63) -> 0.17469388 | N63: 131 | O63: =N63/(D63+F63+H63+J63+L63+N63) -> 0.053469388 | P63: =SUM(D63:N63) -> 2451.0379
A64: 2019 | B64: Vente.8 | C64: Population | D64: 799145 | E64: =D64/(D64+H64+J64+L64+N64) -> 0.42219163 | F64: 318714 | G64: =F64/(D64+F64+H64+J64+L64+N64) -> 0.14411256 | H64: 343955 | I64: =H64/(D64+F64+J64+L64+N64) -> 0.18416873 | J64: 176850 | K64: =J64/(D64+F64+H64+J64+L64+N64) -> 0.079966069 | L64: 499480 | M64: =L64/(D64+F64+H64+J64+L64+N64) -> 0.22584932 | N64: 73419 | O64: =N64/(D64+F64+H64+J64+L64+N64) -> 0.033197788 | P64: =SUM(D64:N64) -> 2211564.1
A65: 2020 | B65: Répartition | C65: Répartiton | D65: 38139600 | E65: =D65/(D65+H65+J65+L65+N65) -> 0.3524798 | F65: 19152190 | G65: =F65/(D65+F65+H65+J65+L65+N65) -> 0.15038329 | H65: 20402610 | I65: =H65/(D65+F65+J65+L65+N65) -> 0.19076199 | J65: 12845350 | K65: =J65/(D65+F65+H65+J65+L65+N65) -> 0.10086189 | L65: 31155300 | M65: =L65/(D65+F65+H65+J65+L65+N65) -> 0.2446319 | N65: 5660787 | O65: =N65/(D65+F65+H65+J65+L65+N65) -> 0.044448587 | P65: =SUM(D65:N65)+Q65 -> 136339338 | Q65: 8983500 | S65: 64760298 | T65: 7785600 | U65: 11505248 | V65: 26552432 | X65: 12535745 | Y65: 2516800 | Z65: 7563814 | AA65: 3119400
A66: 2020 | B66: Vente.1 | C66: Billets Instantanés | D66: 50971203 | E66: =D66/(D66+H66+J66+L66+N66) -> 0.4467069 | F66: 14767275 | G66: =F66/(D66+F66+H66+J66+L66+N66) -> 0.11458903 | H66: 25854942 | I66: =H66/(D66+F66+J66+L66+N66) -> 0.25097819 | J66: 12591039 | K66: =J66/(D66+F66+H66+J66+L66+N66) -> 0.097702179 | L66: 19511729 | M66: =L66/(D66+F66+H66+J66+L66+N66) -> 0.15140438 | N66: 5175442 | O66: =N66/(D66+F66+H66+J66+L66+N66) -> 0.040159669 | P66: =SUM(D66:N66) -> 1.2887163e+08
A67: 2020 | B67: Vente.2 | C67: Jeux de tirages | D67: 56289239 | E67: =D67/(D67+H67+J67+L67+N67) -> 0.42010462 | F67: 19541938 | G67: =F67/(D67+F67+H67+J67+L67+N67) -> 0.1272837 | H67: 30242134 | I67: =H67/(D67+F67+J67+L67+N67) -> 0.24529581 | J67: 12564859 | K67: =J67/(D67+F67+H67+J67+L67+N67) -> 0.081839466 | L67: 29467044 | M67: =L67/(D67+F67+H67+J67+L67+N67) -> 0.1919295 | N67: 5425345 | O67: =N67/(D67+F67+H67+J67+L67+N67) -> 0.035337232 | P67: =SUM(D67:N67) -> 1.5353056e+08
A68: 2020 | B68: Vente.3 | C68: Paris sportifs | D68: 9622958 | E68: =D68/(D68+H68+J68+L68+N68) -> 0.41577417 | F68: 2551286 | G68: =F68/(D68+F68+H68+J68+L68+N68) -> 0.099287433 | H68: 3969153 | I68: =H68/(D68+F68+J68+L68+N68) -> 0.18268459 | J68: 1923134 | K68: =J68/(D68+F68+H68+J68+L68+N68) -> 0.074841879 | L68: 6992439 | M68: =L68/(D68+F68+H68+J68+L68+N68) -> 0.27212211 | N68: 636991 | O68: =N68/(D68+F68+H68+J68+L68+N68) -> 0.024789538 | P68: =SUM(D68:N68) -> 25695962
A69: 2020 | B69: Vente.4 | C69: Loterie électronique | D69: 16961505 | E69: =D69/(D69+H69+J69+L69+N69) -> 0.43304343 | F69: 3380696 | G69: =F69/(D69+F69+H69+J69+L69+N69) -> 0.079454492 | H69: 7029184 | I69: =H69/(D69+F69+J69+L69+N69) -> 0.19789564 | J69: 3976739 | K69: =J69/(D69+F69+H69+J69+L69+N69) -> 0.093462937 | L69: 9981183 | M69: =L69/(D69+F69+H69+J69+L69+N69) -> 0.23458182 | N69: 1219527 | O69: =N69/(D69+F69+H69+J69+L69+N69) -> 0.02866182 | P69: =SUM(D69:N69) -> 42548835
A70: 2020 | B70: Vente.5 | C70: PMUR | D70: 8756125 | E70: =D70/(D70+H70+J70+L70+N70) -> 0.39016762 | F70: 1198940 | G70: =F70/(D70+F70+H70+J70+L70+N70) -> 0.050714658 | H70: 2789143 | I70: =H70/(D70+F70+J70+L70+N70) -> 0.13376059 | J70: 3065936 | K70: =J70/(D70+F70+H70+J70+L70+N70) -> 0.1296878 | L70: 7083919 | M70: =L70/(D70+F70+H70+J70+L70+N70) -> 0.29964679 | N70: 746834 | O70: =N70/(D70+F70+H70+J70+L70+N70) -> 0.031590764 | P70: =SUM(D70:N70) -> 23640898
A71: 2020 | B71: Vente.6 | C71: Total | D71: =SUM(D66:D70) -> 142601030 | E71: =D71/(D71+H71+J71+L71+N71) -> 0.42842721 | F71: =SUM(F66:F70) -> 41440135 | G71: =F71/(D71+F71+H71+J71+L71+N71) -> 0.11071728 | H71: =SUM(H66:H70) -> 69884556 | I71: =H71/(D71+F71+J71+L71+N71) -> 0.22957882 | J71: =SUM(J66:J70) -> 34121707 | K71: =J71/(D71+F71+H71+J71+L71+N71) -> 0.091164338 | L71: =SUM(L66:L70) -> 73036314 | M71: =L71/(D71+F71+H71+J71+L71+N71) -> 0.19513406 | N71: =SUM(N66:N70) -> 13204139 | O71: =N71/(D71+F71+H71+J71+L71+N71) -> 0.03527803 | P71: =SUM(P66:P70) -> 3.7428789e+08 | R71: =Total!W29*1000000 -> 620025340
A72: 2020 | B72: Vente.7 | C72: Point de vente | D72: 880 | E72: =D72/(D72+H72+J72+L72+N72) -> 0.41489863 | F72: 279 | G72: =F72/(D72+F72+H72+J72+L72+N72) -> 0.11625 | H72: 472 | I72: =H72/(D72+F72+J72+L72+N72) -> 0.24481328 | J72: 226 | K72: =J72/(D72+F72+H72+J72+L72+N72) -> 0.094166667 | L72: 420 | M72: =L72/(D72+F72+H72+J72+L72+N72) -> 0.175 | N72: 123 | O72: =N72/(D72+F72+H72+J72+L72+N72) -> 0.05125 | P72: =SUM(D72:N72) -> 2401.0451
A73: 2020 | B73: Vente.8 | C73: Population | D73: 805098 | E73: =D73/(D73+H73+J73+L73+N73) -> 0.42266112 | F73: 321783 | G73: =F73/(D73+F73+H73+J73+L73+N73) -> 0.14451674 | H73: 345525 | I73: =H73/(D73+F73+J73+L73+N73) -> 0.18368349 | J73: 176496 | K73: =J73/(D73+F73+H73+J73+L73+N73) -> 0.079266546 | L73: 504128 | M73: =L73/(D73+F73+H73+J73+L73+N73) -> 0.22641015 | N73: 73584 | O73: =N73/(D73+F73+H73+J73+L73+N73) -> 0.033047488 | P73: =SUM(D73:N73) -> 2226615.1
A74: 2021 | B74: Répartition | C74: Répartiton | D74: 31055090 | E74: =D74/(D74+H74+J74+L74+N74) -> 0.27484566 | F74: 20134371 | G74: =F74/(D74+F74+H74+J74+L74+N74) -> 0.15124366 | H74: 31858269 | I74: =H74/(D74+F74+J74+L74+N74) -> 0.31459639 | J74: 10213450 | K74: =J74/(D74+F74+H74+J74+L74+N74) -> 0.076720529 | L74: 35737415 | M74: =L74/(D74+F74+H74+J74+L74+N74) -> 0.26844929 | N74: 4126790 | O74: =N74/(D74+F74+H74+J74+L74+N74) -> 0.030999272 | P74: =SUM(D74:N74)+Q74 -> 1.4379439e+08 | Q74: 10669000 | S74: 61334695 | T74: 12645500 | U74: 11157007 | V74: 28448659 | X74: 9908400 | Y74: 2412000 | Z74: 13678624 | AA74: 4209500
A75: 2021 | B75: Vente.1 | C75: Billets Instantanés | D75: 54124929 | E75: =D75/(D75+H75+J75+L75+N75) -> 0.4428502 | F75: 16056759 | G75: =F75/(D75+F75+H75+J75+L75+N75) -> 0.11612087 | H75: 27640692 | I75: =H75/(D75+F75+J75+L75+N75) -> 0.24983551 | J75: 13226311 | K75: =J75/(D75+F75+H75+J75+L75+N75) -> 0.095651353 | L75: 21637615 | M75: =L75/(D75+F75+H75+J75+L75+N75) -> 0.15648106 | N75: 5589950 | O75: =N75/(D75+F75+H75+J75+L75+N75) -> 0.040425957 | P75: =SUM(D75:N75) -> 1.3827626e+08
A76: 2021 | B76: Vente.2 | C76: Jeux de tirages | D76: 58035612 | E76: =D76/(D76+H76+J76+L76+N76) -> 0.42053349 | F76: 20254762 | G76: =F76/(D76+F76+H76+J76+L76+N76) -> 0.1279845 | H76: 30963420 | I76: =H76/(D76+F76+J76+L76+N76) -> 0.24323939 | J76: 12626337 | K76: =J76/(D76+F76+H76+J76+L76+N76) -> 0.079782493 | L76: 30800901 | M76: =L76/(D76+F76+H76+J76+L76+N76) -> 0.19462277 | N76: 5578463 | O76: =N76/(D76+F76+H76+J76+L76+N76) -> 0.035248836 | P76: =SUM(D76:N76) -> 1.582595e+08
A77: 2021 | B77: Vente.3 | C77: Paris sportifs | D77: 14821534 | E77: =D77/(D77+H77+J77+L77+N77) -> 0.42381048 | F77: 3583409 | G77: =F77/(D77+F77+H77+J77+L77+N77) -> 0.092941604 | H77: 5812414 | I77: =H77/(D77+F77+J77+L77+N77) -> 0.17751583 | J77: 2887357 | K77: =J77/(D77+F77+H77+J77+L77+N77) -> 0.074888351 | L77: 10490029 | M77: =L77/(D77+F77+H77+J77+L77+N77) -> 0.27207615 | N77: 960746 | O77: =N77/(D77+F77+H77+J77+L77+N77) -> 0.024918527 | P77: =SUM(D77:N77) -> 38555490
A78: 2021 | B78: Vente.4 | C78: Loterie électronique | D78: 14367364 | E78: =D78/(D78+H78+J78+L78+N78) -> 0.4392448 | F78: 2844365 | G78: =F78/(D78+F78+H78+J78+L78+N78) -> 0.080002152 | H78: 5389082 | I78: =H78/(D78+F78+J78+L78+N78) -> 0.17865629 | J78: 3372023 | K78: =J78/(D78+F78+H78+J78+L78+N78) -> 0.094843347 | L78: 8577656 | M78: =L78/(D78+F78+H78+J78+L78+N78) -> 0.2412598 | N78: 1003116 | O78: =N78/(D78+F78+H78+J78+L78+N78) -> 0.028214185 | P78: =SUM(D78:N78) -> 35553607
A79: 2021 | B79: Vente.5 | C79: PMUR | D79: 9650682 | E79: =D79/(D79+H79+J79+L79+N79) -> 0.38157582 | F79: 1054765 | G79: =F79/(D79+F79+H79+J79+L79+N79) -> 0.040034479 | H79: 3134927 | I79: =H79/(D79+F79+J79+L79+N79) -> 0.13505929 | J79: 3382301 | K79: =J79/(D79+F79+H79+J79+L79+N79) -> 0.12837804 | L79: 8451085 | M79: =L79/(D79+F79+H79+J79+L79+N79) -> 0.32076793 | N79: 672655 | O79: =N79/(D79+F79+H79+J79+L79+N79) -> 0.025531178 | P79: =SUM(D79:N79) -> 26346416
A80: 2021 | B80: Vente.6 | C80: Total | D80: =SUM(D75:D79) -> 151000121 | E80: =D80/(D80+H80+J80+L80+N80) -> 0.42752355 | F80: =SUM(F75:F79) -> 43794060 | G80: =F80/(D80+F80+H80+J80+L80+N80) -> 0.11031492 | H80: =SUM(H75:H79) -> 72940535 | I80: =H80/(D80+F80+J80+L80+N80) -> 0.22508987 | J80: =SUM(J75:J79) -> 35494329 | K80: =J80/(D80+F80+H80+J80+L80+N80) -> 0.089408338 | L80: =SUM(L75:L79) -> 79957286 | M80: =L80/(D80+F80+H80+J80+L80+N80) -> 0.20140818 | N80: =SUM(N75:N79) -> 13804930 | O80: =N80/(D80+F80+H80+J80+L80+N80) -> 0.034773889 | P80: =SUM(P75:P79) -> 3.9699127e+08 | R80: =Total!X29*1000000 -> 699493234
A81: 2021 | B81: Vente.7 | C81: Point de vente | D81: 876 | E81: =D81/(D81+H81+J81+L81+N81) -> 0.4137931 | F81: 283 | G81: =F81/(D81+F81+H81+J81+L81+N81) -> 0.11791667 | H81: 475 | I81: =H81/(D81+F81+J81+L81+N81) -> 0.24675325 | J81: 222 | K81: =J81/(D81+F81+H81+J81+L81+N81) -> 0.0925 | L81: 424 | M81: =L81/(D81+F81+H81+J81+L81+N81) -> 0.17666667 | N81: 120 | O81: =N81/(D81+F81+H81+J81+L81+N81) -> 0.05 | P81: =SUM(D81:N81) -> 2401.0476
A82: 2021 | B82: Vente.8 | C82: Population | D82: 814762 | E82: =D82/(D82+H82+J82+L82+N82) -> 0.42452966 | F82: 325496 | G82: =F82/(D82+F82+H82+J82+L82+N82) -> 0.14500601 | H82: 348503 | I82: =H82/(D82+F82+J82+L82+N82) -> 0.18378982 | J82: 175894 | K82: =J82/(D82+F82+H82+J82+L82+N82) -> 0.078359447 | L82: 506343 | M82: =L82/(D82+F82+H82+J82+L82+N82) -> 0.22557198 | N82: 73709 | O82: =N82/(D82+F82+H82+J82+L82+N82) -> 0.032836802 | P82: =SUM(D82:N82) -> 2244708.1
A83: 2022 | B83: Répartition | C83: Répartiton | D83: 32104500 | E83: =D83/(D83+H83+J83+L83+N83) -> 0.2833302 | F83: 22557977 | G83: =F83/(D83+F83+H83+J83+L83+N83) -> 0.16602712 | H83: 30190866 | I83: =H83/(D83+F83+J83+L83+N83) -> 0.28568635 | J83: 11650300 | K83: =J83/(D83+F83+H83+J83+L83+N83) -> 0.08574642 | L83: 35208336 | M83: =L83/(D83+F83+H83+J83+L83+N83) -> 0.25913399 | N83: 4157250 | O83: =N83/(D83+F83+H83+J83+L83+N83) -> 0.030597436 | P83: =SUM(D83:N83)+Q83 -> 1.4564903e+08 | Q83: 9779800 | S83: 72377287 | T83: 10299400 | U83: 11024027 | V83: 26888531 | X83: 8258200 | Y83: 3984450 | Z83: 10827134 | AA83: 1990000
A84: 2022 | B84: Vente.1 | C84: Billets Instantanés | D84: 52237984 | E84: =D84/(D84+H84+J84+L84+N84) -> 0.43694839 | F84: 15922699 | G84: =F84/(D84+F84+H84+J84+L84+N84) -> 0.11753278 | H84: 27782279 | I84: =H84/(D84+F84+J84+L84+N84) -> 0.25797842 | J84: 12516461 | K84: =J84/(D84+F84+H84+J84+L84+N84) -> 0.092389767 | L84: 21707837 | M84: =L84/(D84+F84+H84+J84+L84+N84) -> 0.16023555 | N84: 5307278 | O84: =N84/(D84+F84+H84+J84+L84+N84) -> 0.039175465 | P84: =SUM(D84:N84) -> 1.3547454e+08
A85: 2022 | B85: Vente.2 | C85: Jeux de tirages | D85: 61282981 | E85: =D85/(D85+H85+J85+L85+N85) -> 0.42235804 | F85: 21162231 | G85: =F85/(D85+F85+H85+J85+L85+N85) -> 0.12728437 | H85: 33088779 | I85: =H85/(D85+F85+J85+L85+N85) -> 0.24846895 | J85: 13253559 | K85: =J85/(D85+F85+H85+J85+L85+N85) -> 0.07971612 | L85: 31463027 | M85: =L85/(D85+F85+H85+J85+L85+N85) -> 0.18924052 | N85: 6008882 | O85: =N85/(D85+F85+H85+J85+L85+N85) -> 0.036141595 | P85: =SUM(D85:N85) -> 1.6625946e+08
A86: 2022 | B86: Vente.3 | C86: Paris sportifs | D86: 15669663 | E86: =D86/(D86+H86+J86+L86+N86) -> 0.41871411 | F86: 4008590 | G86: =F86/(D86+F86+H86+J86+L86+N86) -> 0.096751324 | H86: 5887695 | I86: =H86/(D86+F86+J86+L86+N86) -> 0.16564436 | J86: 3407728 | K86: =J86/(D86+F86+H86+J86+L86+N86) -> 0.082248919 | L86: 11586558 | M86: =L86/(D86+F86+H86+J86+L86+N86) -> 0.27965315 | N86: 871654 | O86: =N86/(D86+F86+H86+J86+L86+N86) -> 0.02103824 | P86: =SUM(D86:N86) -> 41431889
A87: 2022 | B87: Vente.4 | C87: Loterie électronique | D87: 25836818 | E87: =D87/(D87+H87+J87+L87+N87) -> 0.44761055 | F87: 4860112 | G87: =F87/(D87+F87+H87+J87+L87+N87) -> 0.077660201 | H87: 9786546 | I87: =H87/(D87+F87+J87+L87+N87) -> 0.18536806 | J87: 5841766 | K87: =J87/(D87+F87+H87+J87+L87+N87) -> 0.093346146 | L87: 14340189 | M87: =L87/(D87+F87+H87+J87+L87+N87) -> 0.22914327 | N87: 1916328 | O87: =N87/(D87+F87+H87+J87+L87+N87) -> 0.030621191 | P87: =SUM(D87:N87) -> 62581760
A88: 2022 | B88: Vente.5 | C88: PMUR | D88: 10694566 | E88: =D88/(D88+H88+J88+L88+N88) -> 0.37839825 | F88: 1473772 | G88: =F88/(D88+F88+H88+J88+L88+N88) -> 0.049561048 | H88: 3391347 | I88: =H88/(D88+F88+J88+L88+N88) -> 0.12872756 | J88: 3853010 | K88: =J88/(D88+F88+H88+J88+L88+N88) -> 0.12957175 | L88: 9550376 | M88: =L88/(D88+F88+H88+J88+L88+N88) -> 0.3211668 | N88: 773427 | O88: =N88/(D88+F88+H88+J88+L88+N88) -> 0.026009351 | P88: =SUM(D88:N88) -> 29736499
A89: 2022 | B89: Vente.6 | C89: Total | D89: =SUM(D84:D88) -> 165722012 | E89: =D89/(D89+H89+J89+L89+N89) -> 0.42705614 | F89: =SUM(F84:F88) -> 47427404 | G89: =F89/(D89+F89+H89+J89+L89+N89) -> 0.1089073 | H89: =SUM(H84:H88) -> 79936646 | I89: =H89/(D89+F89+J89+L89+N89) -> 0.22482691 | J89: =SUM(J84:J88) -> 38872524 | K89: =J89/(D89+F89+H89+J89+L89+N89) -> 0.089262777 | L89: =SUM(L84:L88) -> 88647987 | M89: =L89/(D89+F89+H89+J89+L89+N89) -> 0.20356192 | N89: =SUM(N84:N88) -> 14877569 | O89: =N89/(D89+F89+H89+J89+L89+N89) -> 0.034163285 | P89: =SUM(P84:P88) -> 4.3548415e+08 | R89: =Total!Y29*1000000 -> 736542402
A90: 2022 | B90: Vente.7 | C90: Point de vente | D90: 886 | E90: =D90/(D90+H90+J90+L90+N90) -> 0.41792453 | F90: 280 | G90: =F90/(D90+F90+H90+J90+L90+N90) -> 0.11666667 | H90: 484 | I90: =H90/(D90+F90+J90+L90+N90) -> 0.2526096 | J90: 207 | K90: =J90/(D90+F90+H90+J90+L90+N90) -> 0.08625 | L90: 427 | M90: =L90/(D90+F90+H90+J90+L90+N90) -> 0.17791667 | N90: 116 | O90: =N90/(D90+F90+H90+J90+L90+N90) -> 0.048333333 | P90: =SUM(D90:N90) -> 2401.0514
A91: 2022 | B91: Vente.8 | C91: Population | D91: 822968 | E91: =D91/(D91+H91+J91+L91+N91) -> 0.42517704 | F91: 329809 | G91: =F91/(D91+F91+H91+J91+L91+N91) -> 0.14558546 | H91: 353209 | I91: =H91/(D91+F91+J91+L91+N91) -> 0.18471448 | J91: 176166 | K91: =J91/(D91+F91+H91+J91+L91+N91) -> 0.077763819 | L91: 509448 | M91: =L91/(D91+F91+H91+J91+L91+N91) -> 0.22488234 | N91: 73798 | O91: =N91/(D91+F91+H91+J91+L91+N91) -> 0.032576174 | P91: =SUM(D91:N91) -> 2265399.1
A92: 2023 | B92: Répartition | C92: Répartiton | D92: 62644138 | E92: =D92/(D92+H92+J92+L92+N92) -> 0.35892837 | F92: 27037002 | G92: =F92/(D92+F92+H92+J92+L92+N92) -> 0.13413338 | H92: 34858894 | I92: =H92/(D92+F92+J92+L92+N92) -> 0.20910008 | J92: 16838496 | K92: =J92/(D92+F92+H92+J92+L92+N92) -> 0.083537533 | L92: 53014828 | M92: =L92/(D92+F92+H92+J92+L92+N92) -> 0.26301209 | N92: 7174672 | O92: =N92/(D92+F92+H92+J92+L92+N92) -> 0.035594295 | P92: =SUM(D92:N92)+Q92 -> 213023529 | Q92: 11455498 | S92: 75884145 | T92: 13483031 | U92: 13784508 | V92: 33194459 | W92: 37980988 | X92: 15632000 | Y92: 5752460 | Z92: 8582524 | AA92: 8729413
A93: 2023 | B93: Vente.1 | C93: Billets Instantanés | D93: 51798690 | E93: =D93/(D93+H93+J93+L93+N93) -> 0.434623 | F93: 16098077 | G93: =F93/(D93+F93+H93+J93+L93+N93) -> 0.11899925 | H93: 27899521 | I93: =H93/(D93+F93+J93+L93+N93) -> 0.25982217 | J93: 12056057 | K93: =J93/(D93+F93+H93+J93+L93+N93) -> 0.089120067 | L93: 22115228 | M93: =L93/(D93+F93+H93+J93+L93+N93) -> 0.16347887 | N93: 5311242 | O93: =N93/(D93+F93+H93+J93+L93+N93) -> 0.039261447 | P93: =SUM(D93:N93) -> 1.3527882e+08
A94: 2023 | B94: Vente.2 | C94: Jeux de tirages | D94: 55834811 | E94: =D94/(D94+H94+J94+L94+N94) -> 0.41983824 | F94: 19321903 | G94: =F94/(D94+F94+H94+J94+L94+N94) -> 0.12685643 | H94: 31136909 | I94: =H94/(D94+F94+J94+L94+N94) -> 0.25695556 | J94: 11961287 | K94: =J94/(D94+F94+H94+J94+L94+N94) -> 0.078530889 | L94: 28681258 | M94: =L94/(D94+F94+H94+J94+L94+N94) -> 0.18830454 | N94: 5376982 | O94: =N94/(D94+F94+H94+J94+L94+N94) -> 0.035302152 | P94: =SUM(D94:N94) -> 1.5231315e+08
A95: 2023 | B95: Vente.3 | C95: Paris sportifs | D95: 16356736 | E95: =D95/(D95+H95+J95+L95+N95) -> 0.41091709 | F95: 4179408 | G95: =F95/(D95+F95+H95+J95+L95+N95) -> 0.095019264 | H95: 5495582 | I95: =H95/(D95+F95+J95+L95+N95) -> 0.14278219 | J95: 2921415 | K95: =J95/(D95+F95+H95+J95+L95+N95) -> 0.066418666 | L95: 14056730 | M95: =L95/(D95+F95+H95+J95+L95+N95) -> 0.31958118 | N95: 974978 | O95: =N95/(D95+F95+H95+J95+L95+N95) -> 0.022166224 | P95: =SUM(D95:N95) -> 43984850
A96: 2023 | B96: Vente.4 | C96: Loterie électronique | D96: 24542956 | E96: =D96/(D96+H96+J96+L96+N96) -> 0.44717281 | F96: 4632208 | G96: =F96/(D96+F96+H96+J96+L96+N96) -> 0.077830088 | H96: 8787363 | I96: =H96/(D96+F96+J96+L96+N96) -> 0.17321975 | J96: 5467785 | K96: =J96/(D96+F96+H96+J96+L96+N96) -> 0.091869404 | L96: 14243326 | M96: =L96/(D96+F96+H96+J96+L96+N96) -> 0.23931553 | N96: 1843293 | O96: =N96/(D96+F96+H96+J96+L96+N96) -> 0.030970901 | P96: =SUM(D96:N96) -> 59516932
A97: 2023 | B97: Vente.5 | C97: PMUR | D97: 10207222 | E97: =D97/(D97+H97+J97+L97+N97) -> 0.36411644 | F97: 1581415 | G97: =F97/(D97+F97+H97+J97+L97+N97) -> 0.053400446 | H97: 3080430 | I97: =H97/(D97+F97+J97+L97+N97) -> 0.11609441 | J97: 3978970 | K97: =J97/(D97+F97+H97+J97+L97+N97) -> 0.13435991 | L97: 9926540 | M97: =L97/(D97+F97+H97+J97+L97+N97) -> 0.33519453 | N97: 839689 | O97: =N97/(D97+F97+H97+J97+L97+N97) -> 0.028354206 | P97: =SUM(D97:N97) -> 29614267
A98: 2023 | B98: Vente.6 | C98: Total | D98: =SUM(D93:D97) -> 158740415 | E98: =D98/(D98+H98+J98+L98+N98) -> 0.42342633 | F98: =SUM(F93:F97) -> 45813011 | G98: =F98/(D98+F98+H98+J98+L98+N98) -> 0.10889503 | H98: =SUM(H93:H97) -> 76399805 | I98: =H98/(D98+F98+J98+L98+N98) -> 0.22189365 | J98: =SUM(J93:J97) -> 36385514 | K98: =J98/(D98+F98+H98+J98+L98+N98) -> 0.086486383 | L98: =SUM(L93:L97) -> 89023082 | M98: =L98/(D98+F98+H98+J98+L98+N98) -> 0.21160301 | N98: =SUM(N93:N97) -> 14346184 | O98: =N98/(D98+F98+H98+J98+L98+N98) -> 0.034100097 | P98: =SUM(P93:P97) -> 4.2070802e+08 | R98: =Total!Z29*1000000 -> 738153115
A99: 2023 | B99: Vente.7 | C99: Point de vente | D99: 862 | E99: =D99/(D99+H99+J99+L99+N99) -> 0.41303306 | F99: 272 | G99: =F99/(D99+F99+H99+J99+L99+N99) -> 0.11530309 | H99: 473 | I99: =H99/(D99+F99+J99+L99+N99) -> 0.25079533 | J99: 207 | K99: =J99/(D99+F99+H99+J99+L99+N99) -> 0.087749046 | L99: 436 | M99: =L99/(D99+F99+H99+J99+L99+N99) -> 0.18482408 | N99: 109 | O99: =N99/(D99+F99+H99+J99+L99+N99) -> 0.04620602 | P99: =SUM(D99:N99) -> 2360.0517
A100: 2023 | B100: Vente.8 | C100: Population | D100: 830431 | E100: =D100/(D100+H100+J100+L100+N100) -> 0.42536841 | F100: 334465 | G100: =F100/(D100+F100+H100+J100+L100+N100) -> 0.14626357 | H100: 357282 | I100: =H100/(D100+F100+J100+L100+N100) -> 0.18517336 | J100: 176571 | K100: =J100/(D100+F100+H100+J100+L100+N100) -> 0.077215567 | L100: 514114 | M100: =L100/(D100+F100+H100+J100+L100+N100) -> 0.22482516 | N100: 73865 | O100: =N100/(D100+F100+H100+J100+L100+N100) -> 0.032301612 | P100: =SUM(D100:N100) -> 2286729.1
...

Sheet par habitant
A1: Dépense par habitant pour la Loro
A2: Canton | B2: 2013 | C2: 2014 | D2: 2015 | E2: 2016 | F2: 2017 | G2: 2018 | H2: 2019 | I2: 2020 | J2: 2021 | K2: 2022 | L2: 2023 | M2: 2024
A3: Vaud | B3: ='Détail'!D8/'Détail'!D10 -> 198.03506 | C3: ='Détail'!D$17/'Détail'!D$19 -> 199.10221 | D3: ='Détail'!D$26/'Détail'!D$28 -> 189.5157 | E3: ='Détail'!D$35/'Détail'!D$37 -> 196.28906 | F3: ='Détail'!D$44/'Détail'!D$46 -> 189.26975 | G3: ='Détail'!D$53/'Détail'!D$55 -> 187.18778 | H3: ='Détail'!D$62/'Détail'!D$64 -> 196.54186 | I3: ='Détail'!D$71/'Détail'!D$73 -> 177.12257 | J3: ='Détail'!D$80/'Détail'!D$82 -> 185.33034 | K3: ='Détail'!D$89/'Détail'!D$91 -> 201.37115 | L3: ='Détail'!D$98/'Détail'!D$100 -> 191.15425 | M3: ='Détail'!D$107/'Détail'!D$109 -> 193.80635
A4: Fribourg | B4: ='Détail'!F8/'Détail'!F10 -> 124.81936 | C4: ='Détail'!F$17/'Détail'!F$19 -> 129.90475 | D4: ='Détail'!F$26/'Détail'!F$28 -> 124.8328 | E4: ='Détail'!F$35/'Détail'!F$37 -> 133.03627 | F4: ='Détail'!F$44/'Détail'!F$46 -> 127.64739 | G4: ='Détail'!F$53/'Détail'!F$55 -> 128.36699 | H4: ='Détail'!F$62/'Détail'!F$64 -> 134.47671 | I4: ='Détail'!F$71/'Détail'!F$73 -> 128.78286 | J4: ='Détail'!F$80/'Détail'!F$82 -> 134.54562 | K4: ='Détail'!F$89/'Détail'!F$91 -> 143.80264 | L4: ='Détail'!F$98/'Détail'!F$100 -> 136.97401 | M4: ='Détail'!F$107/'Détail'!F$109 -> 144.19995
A5: Valais | B5: ='Détail'!H8/'Détail'!H10 -> 232.15384 | C5: ='Détail'!H$17/'Détail'!H$19 -> 230.1104 | D5: ='Détail'!H$26/'Détail'!H$28 -> 218.33792 | E5: ='Détail'!H$35/'Détail'!H$37 -> 231.10593 | F5: ='Détail'!H$44/'Détail'!H$46 -> 216.88101 | G5: ='Détail'!H$53/'Détail'!H$55 -> 215.91945 | H5: ='Détail'!H$62/'Détail'!H$64 -> 221.44568 | I5: ='Détail'!H$71/'Détail'!H$73 -> 202.25615 | J5: ='Détail'!H$80/'Détail'!H$82 -> 209.29672 | K5: ='Détail'!H$89/'Détail'!H$91 -> 226.31543 | L5: ='Détail'!H$98/'Détail'!H$100 -> 213.83614 | M5: ='Détail'!H$107/'Détail'!H$109 -> 217.16404
A6: Neuchâtel | B6: ='Détail'!J8/'Détail'!J10 -> 207.37901 | C6: ='Détail'!J17/'Détail'!J$19 -> 203.51213 | D6: ='Détail'!J$26/'Détail'!J$28 -> 196.72686 | E6: ='Détail'!J$35/'Détail'!J$37 -> 203.94873 | F6: ='Détail'!J$44/'Détail'!J$46 -> 196.30338 | G6: ='Détail'!J$53/'Détail'!J$55 -> 198.33063 | H6: ='Détail'!J$62/'Détail'!J$64 -> 206.7956 | I6: ='Détail'!J$71/'Détail'!J$73 -> 193.3285 | J6: ='Détail'!J$80/'Détail'!J$82 -> 201.79386 | K6: ='Détail'!J$89/'Détail'!J$91 -> 220.65849 | L6: ='Détail'!J$98/'Détail'!J$100 -> 206.06733 | M6: ='Détail'!J$107/'Détail'!J$109 -> 207.0791
A7: Genève | B7: ='Détail'!L8/'Détail'!L10 -> 152.14183 | C7: ='Détail'!L$17/'Détail'!L$19 -> 157.76273 | D7: ='Détail'!L$26/'Détail'!L$28 -> 152.60579 | E7: ='Détail'!L$35/'Détail'!L$37 -> 157.97029 | F7: ='Détail'!L$44/'Détail'!L$46 -> 153.93111 | G7: ='Détail'!L$53/'Détail'!L$55 -> 153.78482 | H7: ='Détail'!L$62/'Détail'!L$64 -> 161.78239 | I7: ='Détail'!L$71/'Détail'!L$73 -> 144.87653 | J7: ='Détail'!L$80/'Détail'!L$82 -> 157.91131 | K7: ='Détail'!L$89/'Détail'!L$91 -> 174.00792 | L7: ='Détail'!L$98/'Détail'!L$100 -> 173.15825 | M7: ='Détail'!L$107/'Détail'!L$109 -> 178.52443
A8: Jura | B8: ='Détail'!N8/'Détail'!N10 -> 205.63405 | C8: ='Détail'!N$17/'Détail'!N$19 -> 203.10041 | D8: ='Détail'!N$26/'Détail'!N$28 -> 199.86364 | E8: ='Détail'!N$35/'Détail'!N$37 -> 208.07812 | F8: ='Détail'!N44/'Détail'!N46 -> 193.66754 | G8: ='Détail'!N$53/'Détail'!N$55 -> 189.21213 | H8: ='Détail'!N$62/'Détail'!N$64 -> 198.67262 | I8: ='Détail'!N$71/'Détail'!N$73 -> 179.44307 | J8: ='Détail'!N$80/'Détail'!N$82 -> 187.28961 | K8: ='Détail'!N$89/'Détail'!N$91 -> 201.59854 | L8: ='Détail'!N$98/'Détail'!N$100 -> 194.22167 | M8: ='Détail'!N$107/'Détail'!N$109 -> 202.04633
A9: Romandie | B9: ='Détail'!P8/'Détail'!P10 -> 183.71613 | C9: ='Détail'!P17/'Détail'!P19 -> 185.33451 | D9: ='Détail'!P26/'Détail'!P$28 -> 177.4361 | E9: ='Détail'!P35/'Détail'!P37 -> 185.08545 | F9: ='Détail'!P44/'Détail'!P46 -> 177.52143 | G9: ='Détail'!P53/'Détail'!P55 -> 176.65413 | H9: ='Détail'!P62/'Détail'!P64 -> 184.51088 | I9: ='Détail'!P71/'Détail'!P73 -> 168.09726 | J9: ='Détail'!P80/'Détail'!P82 -> 176.85652 | K9: ='Détail'!P89/'Détail'!P91 -> 192.23286 | L9: ='Détail'!P98/'Détail'!P100 -> 183.97808 | M9: ='Détail'!P107/'Détail'!P109 -> 188.04336
A12: Dépense par habitant pour la Loterie electronique (Tactilo) - https://www.loterie-electronique.ch/fr/faq#t20n42 | H12: https://www.vd.ch/typo3temp/assets/pdfs/tactilo-les-cantons-romands-rejettent-la-decision-dinterdiction-1168623969.pdf
A13: Canton | B13: 2013 | C13: 2014 | D13: 2015 | E13: 2016 | F13: 2017 | G13: 2018 | H13: 2019 | I13: 2020 | J13: 2021 | K13: 2022 | L13: 2023 | M13: 2024
A14: Vaud | B14: ='Détail'!$D$6/'Détail'!$D$10 -> 48.406499 | C14: ='Détail'!$D$15/'Détail'!$D$19 -> 46.647675 | D14: ='Détail'!$D$24/'Détail'!$D$28 -> 45.428042 | E14: ='Détail'!$D$33/'Détail'!$D$37 -> 45.337187 | F14: ='Détail'!$D$42/'Détail'!$D$46 -> 41.965447 | G14: ='Détail'!$D$51/'Détail'!$D$55 -> 41.6145 | H14: ='Détail'!$D$60/'Détail'!$D$64 -> 38.138365 | I14: ='Détail'!$D$69/'Détail'!$D$73 -> 21.067628 | J14: ='Détail'!$D$78/'Détail'!$D$82 -> 17.633817 | K14: ='Détail'!$D$87/'Détail'!$D$91 -> 31.394681 | L14: ='Détail'!$D$96/'Détail'!$D$100 -> 29.55448 | M14: ='Détail'!$D$105/'Détail'!$D$109 -> 26.711723
A15: Fribourg | B15: ='Détail'!$F$6/'Détail'!$F$10 -> 19.660512 | C15: ='Détail'!$F$15/'Détail'!$F$19 -> 20.52013 | D15: ='Détail'!$F$24/'Détail'!$F$28 -> 19.803096 | E15: ='Détail'!$F$33/'Détail'!$F$37 -> 20.372714 | F15: ='Détail'!$F$42/'Détail'!$F$46 -> 20.071658 | G15: ='Détail'!$F$51/'Détail'!$F$55 -> 19.472092 | H15: ='Détail'!$F$60/'Détail'!$F$64 -> 18.390883 | I15: ='Détail'!$F$69/'Détail'!$F$73 -> 10.506136 | J15: ='Détail'!$F$78/'Détail'!$F$82 -> 8.7385559 | K15: ='Détail'!$F$87/'Détail'!$F$91 -> 14.736141 | L15: ='Détail'!$F$96/'Détail'!$F$100 -> 13.849605 | M15: ='Détail'!$F$105/'Détail'!$F$109 -> 12.121814
A16: Valais | B16: ='Détail'!$H$6/'Détail'!$H$10 -> 54.105336 | C16: ='Détail'!$H$15/'Détail'!$H$19 -> 49.348777 | D16: ='Détail'!$H$24/'Détail'!$H$28 -> 47.515036 | E16: ='Détail'!$H$33/'Détail'!$H$37 -> 47.915358 | F16: ='Détail'!$H$42/'Détail'!$H$46 -> 43.167476 | G16: ='Détail'!$H$51/'Détail'!$H$55 -> 42.329233 | H16: ='Détail'!$H$60/'Détail'!$H$64 -> 36.75548 | I16: ='Détail'!$H$69/'Détail'!$H$73 -> 20.343489 | J16: ='Détail'!$H$78/'Détail'!$H$82 -> 15.463517 | K16: ='Détail'!$H$87/'Détail'!$H$91 -> 27.707522 | L16: ='Détail'!$H$96/'Détail'!$H$100 -> 24.595034 | M16: ='Détail'!$H$105/'Détail'!$H$109 -> 22.08868
A17: Neuchâtel | B17: ='Détail'!$J$6/'Détail'!$J$10 -> 49.898576 | C17: ='Détail'!$J$15/'Détail'!$J$19 -> 48.029773 | D17: ='Détail'!$J$24/'Détail'!$J$28 -> 46.679101 | E17: ='Détail'!$J$33/'Détail'!$J$37 -> 45.141522 | F17: ='Détail'!$J$42/'Détail'!$J$46 -> 43.702123 | G17: ='Détail'!$J$51/'Détail'!$J$55 -> 42.520678 | H17: ='Détail'!$J$60/'Détail'!$J$64 -> 38.493882 | I17: ='Détail'!$J$69/'Détail'!$J$73 -> 22.53161 | J17: ='Détail'!$J$78/'Détail'!$J$82 -> 19.170768 | K17: ='Détail'!$J$87/'Détail'!$J$91 -> 33.160576 | L17: ='Détail'!$J$96/'Détail'!$J$100 -> 30.966495 | M17: ='Détail'!$J$105/'Détail'!$J$109 -> 27.948208
A18: Genève | B18: ='Détail'!$L$6/'Détail'!$L$10 -> 49.617634 | C18: ='Détail'!$L$15/'Détail'!$L$19 -> 45.821762 | D18: ='Détail'!$L$24/'Détail'!$L$28 -> 44.459956 | E18: ='Détail'!$L$33/'Détail'!$L$37 -> 44.126265 | F18: ='Détail'!$L$42/'Détail'!$L$46 -> 41.433162 | G18: ='Détail'!$L$51/'Détail'!$L$55 -> 39.601774 | H18: ='Détail'!$L$60/'Détail'!$L$64 -> 35.864555 | I18: ='Détail'!$L$69/'Détail'!$L$73 -> 19.798906 | J18: ='Détail'!$L$78/'Détail'!$L$82 -> 16.940406 | K18: ='Détail'!$L$87/'Détail'!$L$91 -> 28.148484 | L18: ='Détail'!$L$96/'Détail'!$L$100 -> 27.704606 | M18: ='Détail'!$L$105/'Détail'!$L$109 -> 25.435947
A19: Jura | B19: ='Détail'!N$6/'Détail'!$N$10 -> 43.814313 | C19: ='Détail'!$N$15/'Détail'!$N$19 -> 41.904862 | D19: ='Détail'!$N$24/'Détail'!$N$28 -> 41.912733 | E19: ='Détail'!$N$33/'Détail'!$N$37 -> 41.590434 | F19: ='Détail'!$N$42/'Détail'!$N$46 -> 36.318878 | G19: ='Détail'!$N$51/'Détail'!$N$55 -> 33.468236 | H19: ='Détail'!$N$60/'Détail'!$N$64 -> 32.649505 | I19: ='Détail'!$N$69/'Détail'!$N$73 -> 16.573263 | J19: ='Détail'!$N$78/'Détail'!$N$82 -> 13.609139 | K19: ='Détail'!$N$87/'Détail'!$N$91 -> 25.967208 | L19: ='Détail'!$N$96/'Détail'!$N$100 -> 24.954891 | M19: ='Détail'!N$105/'Détail'!$N$109 -> 23.028519
A20: Romandie | B20: ='Détail'!P$6/'Détail'!$P$10 -> 45.465252 | C20: ='Détail'!$P$15/'Détail'!$P$19 -> 43.120659 | D20: ='Détail'!$P$24/'Détail'!$P$28 -> 41.860451 | E20: ='Détail'!$P$33/'Détail'!$P$37 -> 41.757257 | F20: ='Détail'!$P$42/'Détail'!$P$46 -> 38.849107 | G20: ='Détail'!$P$51/'Détail'!$P$55 -> 37.896638 | H20: ='Détail'!$P$60/'Détail'!$P$64 -> 34.410088 | I20: ='Détail'!$P$69/'Détail'!$P$73 -> 19.109201 | J20: ='Détail'!$P$78/'Détail'!$P$82 -> 15.838856 | K20: ='Détail'!$P$87/'Détail'!$P$91 -> 27.625049 | L20: ='Détail'!$P$96/'Détail'!$P$100 -> 26.027103 | M20: ='Détail'!$P$105/'Détail'!$P$109 -> 23.537519
A23: Dépense par habitant pour les paris sportifs
A24: Canton | B24: 2013 | C24: 2014 | D24: 2015 | E24: 2016 | F24: 2017 | G24: 2018 | H24: 2019 | I24: 2020 | J24: 2021 | K24: 2022 | L24: 2023 | M24: 2024
A25: Vaud | B25: ='Détail'!$D$5/'Détail'!$D$10 -> 2.3088257 | C25: ='Détail'!$D$14/'Détail'!$D$19 -> 2.6856679 | D25: ='Détail'!$D$23/'Détail'!$D$28 -> 2.584572 | E25: ='Détail'!$D$32/'Détail'!$D$37 -> 3.0887476 | F25: ='Détail'!$D$41/'Détail'!$D$46 -> 3.2121385 | G25: ='Détail'!$D$50/'Détail'!$D$55 -> 5.6382291 | H25: ='Détail'!$D$59/'Détail'!$D$64 -> 10.122565 | I25: ='Détail'!$D$68/'Détail'!$D$73 -> 11.95253 | J25: ='Détail'!$D$77/'Détail'!$D$82 -> 18.191244 | K25: ='Détail'!$D$86/'Détail'!$D$91 -> 19.040428 | L25: ='Détail'!$D$95/'Détail'!$D$100 -> 19.696683 | M25: ='Détail'!$D$104/'Détail'!$D$109 -> 24.587072
A26: Fribourg | B26: ='Détail'!$F$5/'Détail'!$F$10 -> 1.6183153 | C26: ='Détail'!$F$14/'Détail'!$F$19 -> 1.7566208 | D26: ='Détail'!$F$23/'Détail'!$F$28 -> 2.4891373 | E26: ='Détail'!$F$32/'Détail'!$F$37 -> 2.696664 | F26: ='Détail'!$F$41/'Détail'!$F$46 -> 2.3146669 | G26: ='Détail'!$F$50/'Détail'!$F$55 -> 4.1099615 | H26: ='Détail'!$F$59/'Détail'!$F$64 -> 6.127936 | I26: ='Détail'!$F$68/'Détail'!$F$73 -> 7.9285916 | J26: ='Détail'!$F$77/'Détail'!$F$82 -> 11.009072 | K26: ='Détail'!$F$86/'Détail'!$F$91 -> 12.154277 | L26: ='Détail'!$F$95/'Détail'!$F$100 -> 12.495801 | M26: ='Détail'!$F$104/'Détail'!$F$109 -> 15.481977
A27: Valais | B27: ='Détail'!$H$5/'Détail'!$H$10 -> 2.818986 | C27: ='Détail'!$H$14/'Détail'!$H$19 -> 3.1568143 | D27: ='Détail'!$H$23/'Détail'!$H$28 -> 3.1882519 | E27: ='Détail'!$H$32/'Détail'!$H$37 -> 3.7617011 | F27: ='Détail'!$H$41/'Détail'!$H$46 -> 3.2146585 | G27: ='Détail'!$H$50/'Détail'!$H$55 -> 6.1407971 | H27: ='Détail'!$H$59/'Détail'!$H$64 -> 7.8743702 | I27: ='Détail'!$H$68/'Détail'!$H$73 -> 11.487311 | J27: ='Détail'!$H$77/'Détail'!$H$82 -> 16.678232 | K27: ='Détail'!$H$86/'Détail'!$H$91 -> 16.669153 | L27: ='Détail'!$H$95/'Détail'!$H$100 -> 15.381637 | M27: ='Détail'!$H$104/'Détail'!$H$109 -> 19.557005
A28: Neuchâtel | B28: ='Détail'!$J$5/'Détail'!$J$10 -> 2.4289561 | C28: ='Détail'!$J$14/'Détail'!$J$19 -> 3.3119863 | D28: ='Détail'!$J$23/'Détail'!$J$28 -> 2.9982687 | E28: ='Détail'!$J$32/'Détail'!$J$37 -> 3.2461386 | F28: ='Détail'!$J$41/'Détail'!$J$46 -> 3.5932451 | G28: ='Détail'!$J$50/'Détail'!$J$55 -> 5.1366962 | H28: ='Détail'!$J$59/'Détail'!$J$64 -> 8.0583263 | I28: ='Détail'!$J$68/'Détail'!$J$73 -> 10.89619 | J28: ='Détail'!$J$77/'Détail'!$J$82 -> 16.415324 | K28: ='Détail'!$J$86/'Détail'!$J$91 -> 19.343846 | L28: ='Détail'!$J$95/'Détail'!$J$100 -> 16.545271 | M28: ='Détail'!$J$104/'Détail'!$J$109 -> 21.866494
A29: Genève | B29: ='Détail'!$L$5/'Détail'!$L$10 -> 1.8481713 | C29: ='Détail'!$L$14/'Détail'!$L$19 -> 3.141264 | D29: ='Détail'!$L$23/'Détail'!$L$28 -> 3.4249861 | E29: ='Détail'!$L$32/'Détail'!$L$37 -> 3.9552127 | F29: ='Détail'!$L$41/'Détail'!$L$46 -> 3.8373645 | G29: ='Détail'!$L$50/'Détail'!$L$55 -> 7.4137595 | H29: ='Détail'!$L$59/'Détail'!$L$64 -> 10.319933 | I29: ='Détail'!$L$68/'Détail'!$L$73 -> 13.870364 | J29: ='Détail'!$L$77/'Détail'!$L$82 -> 20.717239 | K29: ='Détail'!$L$86/'Détail'!$L$91 -> 22.743358 | L29: ='Détail'!$L$95/'Détail'!$L$100 -> 27.34166 | M29: ='Détail'!$L$104/'Détail'!$L$109 -> 31.225823
A30: Jura | B30: ='Détail'!N$5/'Détail'!$N$10 -> 1.5184658 | C30: ='Détail'!$N$14/'Détail'!$N$19 -> 1.5174524 | D30: ='Détail'!$N$23/'Détail'!$N$28 -> 1.9240436 | E30: ='Détail'!$N$32/'Détail'!$N$37 -> 2.1809926 | F30: ='Détail'!$N$41/'Détail'!$N$46 -> 2.2295752 | G30: ='Détail'!$N$50/'Détail'!$N$55 -> 4.3851822 | H30: ='Détail'!$N$59/'Détail'!$N$64 -> 6.3431401 | I30: ='Détail'!$N$68/'Détail'!$N$73 -> 8.6566509 | J30: ='Détail'!$N$77/'Détail'!$N$82 -> 13.034311 | K30: ='Détail'!$N$86/'Détail'!$N$91 -> 11.81135 | L30: ='Détail'!$N$95/'Détail'!$N$100 -> 13.199458 | M30: ='Détail'!N$104/'Détail'!$N$109 -> 17.419703
A31: Romandie | B31: ='Détail'!P$5/'Détail'!$P$10 -> 2.1699656 | C31: ='Détail'!$P$14/'Détail'!$P$19 -> 2.7421389 | D31: ='Détail'!$P$23/'Détail'!$P$28 -> 2.8661812 | E31: ='Détail'!$P$32/'Détail'!$P$37 -> 3.3151803 | F31: ='Détail'!$P$41/'Détail'!$P$46 -> 3.2227891 | G31: ='Détail'!$P$50/'Détail'!$P$55 -> 5.8150483 | H31: ='Détail'!$P$59/'Détail'!$P$64 -> 8.9512705 | I31: ='Détail'!$P$68/'Détail'!$P$73 -> 11.54037 | J31: ='Détail'!$P$77/'Détail'!$P$82 -> 17.176171 | K31: ='Détail'!$P$86/'Détail'!$P$91 -> 18.289002 | L31: ='Détail'!$P$95/'Détail'!$P$100 -> 19.234832 | M31: ='Détail'!$P$104/'Détail'!$P$109 -> 23.519528

Sheet Subv_TdR
B1: Canton | D1: 2013 | E1: 2014 | F1: 2015 | G1: 2016 | H1: 2017 | I1: 2018 | J1: 2019 | K1: 2020 | L1: 2021 | M1: 2022 | N1: 2023 | O1: 2024 | P1: 2025
A2: Tour de Romandie | D2: =SUM(D3:D90) -> 915100.15 | E2: =SUM(E3:E90) -> 933790.43 | F2: =SUM(F3:F90) -> 936964.6 | G2: =SUM(G3:G90) -> 982353 | H2: =SUM(H3:H90) -> 975478 | I2: =SUM(I3:I90) -> 997738 | J2: =SUM(J3:J90) -> 974046 | K2: =SUM(K3:K90) -> 760118 | ... P2: =SUM(P3:P90) -> 0 | Q2: Budget total 2026
A3: Administration communale de Chalais | B3: Valais | C3: Féminin | O3: 6149
A4: Administration communale de Chambéry | B4: Valais | I4: 8300
A5: Administration communale de Saillon | B5: Valais | O5: 1692
A6: Assoc. Courses Cyclistes Lausanne | B6: Vaud | C6: Féminin | M6: 6000 | O6: 6000
A7: Assoc. Courses Cyclistes Lausanne | B7: Vaud | C7: Masculin | M7: 6000
A8: Assoc. Organisation étape Aigle MY Tour de Romandie | L8: 2713
A9: Assoc. pour lorganisation de létape Aigle-Martigny du Tour de Romandie 2021 | L9: 5000
A10: Assoc. pour l’organisation locale d’étapes du tour de Romandie à Bulle | B10: Fribourg | H10: 1000
A11: Assoc. Région Neuchâtel Littoral | B11: Neuchâtel | C11: Féminin | O11: 10000
A12: Assoc. Région Neuchâtel Littoral | B12: Neuchâtel | C12: Masculin | O12: 40000
A13: Assoc. Sport Evènement | B13: Valais | K13: 8118
A14: Assoc. Sport Événement, Vionnaz Torgon | B14: Valais | C14: Féminin | N14: 5053
A15: Assoc. Sport Tourisme Culture Vallorbe-Vallée de Joux | N15: 6000
A16: Assoc. Tour de Romandie Les Diablerets | E16: 1600
A17: Association Tour de Romandie | B17: Neuchatel | E17: 20000
A18: Broye Sport Events | B18: Vaud | C18: Masculin | O18: 6000
A19: Cimes Cycle La Chaux-de-Fonds | G19: 20000
A20: Comité dorganisation Fribourg | M20: 2000
A21: Commune d’Aigle | H21: 7000
A22: Commune dOron | B22: Vaud | C22: Masculin | O22: 7500
A23: Commune dYverdon-les-Bains | B23: Vaud | C23: Féminin | N23: 5500
A24: Commune dYverdon-les-Bains | B24: Vaud | C24: Masculin | I24: 5000
A25: Commune de Château-dOEx | B25: Vaud | C25: Masculin | O25: 2500
A26: Commune de Conthey | B26: Valais | G26: 1350
A27: Commune de Crissier | B27: Vaud | C27: Masculin | N27: 8000
A28: Commune de la Béroche | M28: 15000
A29: Commune de Lausanne | H29: 5500
A30: Commune de Leysin | B30: Vaud | C30: Masculin | H30: 5000 | O30: 7000
A31: Commune de Montreux | E31: 5000
A32: Commune de Morges | B32: Vaud | C32: Féminin | O32: 8000
A33: Commune de Moudon | G33: 7000
A34: Commune de Nyon | B34: Vaud | C34: Féminin | N34: 8000
A35: Commune de Port-Valais | B35: Valais | C35: Masculin | N35: 6589
A36: Commune de Vufflens-la-Ville | B36: Vaud | C36: Masculin | N36: 8000
A37: Cyclophile Romontois | B37: Fribourg | J37: 1000 | M37: 1000
A38: Cyclophile Sédunois, Sion | B38: Valais | G38: 4003 | I38: 4078 | M38: 2361 | N38: 4287
A39: Delémont | B39: Jura | I39: 25000
A40: Etape Ascona Sion | E40: 6190
A41: Etape de Fribourg | B41: Fribourg | O41: 5000
A42: Fond. du Tour de Romandie | B42: Vaud | C42: Masculin | D42: 338714.36 | E42: 333973.61 | F42: 333973.6 | G42: 352213 | H42: 351723 | I42: 353793 | J42: 353314 | K42: 279847 | M42: 361123 | N42: 304200 | O42: 286450
A43: Fond. du Tour de Romandie | B43: Vaud | C43: Féminin | M43: 171058 | N43: 121680 | O43: 101100
A44: Fond. du Tour de Romandie | B44: Fribourg | C44: Masculin | D44: 105712.5 | E44: 107106 | F44: 114966 | G44: 115593 | H44: 116634 | I44: 116986 | J44: 117665 | K44: 94430 | M44: 115435 | O44: 110500
A45: Fond. du Tour de Romandie | B45: Fribourg | C45: Féminin | M45: 54680 | O45: 39000
A46: Fond. du Tour de Romandie | B46: Valais | C46: Masculin | D46: 159742.59 | E46: 159395.81 | F46: 166471 | G46: 165513 | H46: 166602 | I46: 164408 | J46: 164123 | M46: =31503+66507+166267 -> 264277 | N46: =66600+99900 -> 166500 | O46: 88800
A47: Fond. du Tour de Romandie | B47: Valais | C47: Féminin | M47: 78758 | N47: =26640+39960 -> 66600 | O47: 38850
A48: Fond. du Tour de Romandie | B48: Neuchâtel | C48: Masculin | D48: 84449.8 | E48: 81327.48 | F48: 84051 | G48: 83636 | H48: 82625 | I48: 82401 | J48: 81750 | K48: 128319 | M48: 74594 | N48: 74700 | O48: 68000
A49: Fond. du Tour de Romandie | B49: Neuchâtel | C49: Féminin | K49: 63596 | M49: 35334 | N49: 29880 | O49: 24000
A50: Fond. du Tour de Romandie | B50: Genève | C50: Masculin | D50: 178840 | E50: 185292 | F50: 197358 | G50: 198607 | H50: 198265 | I50: 199414 | J50: 200364 | K50: 158954 | M50: 205002 | N50: 209700 | O50: 202300
A51: Fond. du Tour de Romandie | B51: Genève | C51: Féminin | M51: 97106 | N51: 83880 | O51: 71400
A52: Fond. du Tour de Romandie | B52: Jura | O52: 3500
A53: Fond. du Tour de Romandie | B53: Jura | C53: Masculin | D53: 33540.9 | E53: 32905.53 | F53: 34145 | G53: 34438 | H53: 34122 | I53: 33358 | J53: 32830 | K53: 25854 | M53: 27579 | N53: 27900
A54: Fond. du Tour de Romandie | B54: Jura | C54: Féminin | M54: 13064 | N54: 11680
A55: Fond. du Tour de Romandie | B55: Genève | O55: 60000
A56: Fond. Tour de Romandie | B56: Romandie | C56: Soutien exceptionnel CRTS | O56: 30000
A57: Fond. Tour de Romandie | N57: 600000
A58: Mont-sur Rolle | B58: Vaud | C58: Masculin | I58: 5000
A59: Morgins 1875 Assoc. | H59: 7007
A60: Tour de Romandie | B60: Valais | N60: 5079
A61: Tour de Romandie | L61: 950000
A62: Tour de Romandie - Etapes NE | J62: =8000+15000 -> 23000
A63: Tour de Romandie Féminin | L63: 450000
A64: Vallée de Joux-Juraparc | F64: 5000
A65: Vélo-Club Fribourg | B65: Fribourg | E65: 1000 | F65: 1000 | K65: 1000 | L65: 1000 | M65: 1000
A66: Ville de Romont | L66: 10000
A67: Ville de Vernier | B67: Genève | C67: Masculin | O67: 10000
A68: Commune de Bagnes | D68: 7100
A69: Ouest Lausannois Org. dune étape darrivée | D69: 7000

Sheet Subv_Cinéforom
B1: Canton | D1: 2013 | E1: 2014 | F1: 2015 | G1: 2016 | H1: 2017 | I1: 2018 | J1: 2019 | K1: 2020 | L1: 2021 | M1: 2022 | N1: 2023 | O1: 2024 | P1: 2025
A2: Fond. Cinéforom | D2: =SUM(D3:D33) -> 2920000 | E2: =SUM(E3:E33) -> 3015000 | F2: =SUM(F3:F33) -> 3210000 | G2: =SUM(G3:G33) -> 3010000 | H2: =SUM(H3:H33) -> 2660000 | I2: =SUM(I3:I33) -> 2660000 | J2: =SUM(J3:J33) -> 2720000 | K2: =SUM(K3:K33) -> 2660000 | ... P2: =SUM(P3:P33) -> 2800335
A3: Fond. Cinéforom | B3: Conférence des Présidents des Organes de Répartition | D3: 1600000 | E3: 1700000 | F3: 1700000 | G3: 1700000 | H3: 1700000 | I3: 1700000 | J3: 1700000 | K3: 1700000 | L3: 1700000 | M3: 1700000 | N3: 1700000 | O3: 1700000 | P3: 1700000
A4: Fond. Cinéforom | B4: Fribourg | L4: 185000 | M4: 185200 | N4: 185200 | O4: 185200 | P4: 234600
A5: Fond. Cinéforom | B5: Genève | C5: Soutien à la diversité de la production audiovisuelle indépendante | D5: 350000 | E5: 350000 | F5: 550000 | G5: 350000 | M5: 85735 | N5: 85735 | O5: 85735
A6: Fond. Cinéforom | B6: Neuchâtel | L6: 156800 | O6: 50000
A7: Fond. Cinéforom | B7: Jura | O7: 25000
A8: Fond. Cinéforom | B8: Vaud | D8: 700000 | E8: 700000 | F8: 700000 | G8: 700000 | H8: 700000 | I8: 700000 | J8: 700000 | K8: 700000 | L8: 700000 | M8: 700000 | N8: 700000 | O8: 700000 | P8: 700000
A9: Fond. Cinéforom | B9: Fribourg | C9: Soutien à la diversité de la production audiovisuelle indépendante | J9: 80000 | K9: 80000 | L9: 80000 | M9: 80000 | N9: 80000 | O9: 80000 | P9: 80000
A10: Fond. Cinéforom, | B10: Valais | C10: Soutien à la diversité de la production audiovisuelle indépendante | D10: 270000 | E10: 265000 | F10: 260000 | G10: 260000 | H10: 260000 | I10: 260000 | J10: 240000 | K10: 180000 | L10: 130000 | P10: 85735

Sheet Subv_EMS
B1: Canton | D1: 2013 | E1: 2014 | F1: 2015 | G1: 2016 | H1: 2017 | I1: 2018 | J1: 2019 | K1: 2020 | L1: 2021 | M1: 2022 | N1: 2023 | O1: 2024 | P1: 2025
A3: Tertianum La Venise, Monthey | B3: Valais | M3: 16000 | N3: 23000 | O3: 20000 | P3: 26000
A4: Tertianum Les Marronniers, Martigny | B4: Valais | D4: 27300 | E4: 27300 | F4: 26650 | G4: 27300 | H4: 27300 | I4: 27300 | J4: 27300 | K4: 27300 | L4: 27300 | M4: 30000 | N4: 30000 | O4: 31000 | P4: 42000
A5: Tertianum Les Sources, Saxon | B5: Valais | F5: 24050 | G5: 42900 | H5: 44200 | I5: 44200 | J5: 44200 | K5: 44200 | L5: 44200 | M5: 37000 | N5: 39000 | O5: 35000 | P5: 50000
A6: Tertianum Les Tourelles, Martigny | B6: Valais | D6: 23400 | E6: 29250 | F6: 28600 | G6: 29900 | H6: 29900 | I6: 29900 | J6: 29900 | K6: 29900 | L6: 29900 | M6: 29000 | N6: 32000 | O6: 29000 | P6: 38000
A7: EMS Les Vergers, Aproz | B7: Valais | H7: 37700 | I7: 48750 | J7: 48750 | K7: 48750 | L7: 48750

Sheet Subv_musique classique
B1: Canton | D1: 2013 | E1: 2014 | F1: 2015 | G1: 2016 | H1: 2017 | I1: 2018 | J1: 2019 | K1: 2020 | L1: 2021 | M1: 2022 | N1: 2023 | O1: 2024 | P1: 2025
A3: Fond. du Verbier Festival | B3: Valais | D3: 800000 | E3: =775000+150000 -> 925000 | F3: =775000+150000 -> 925000 | G3: =725000 -> 725000 | H3: =775000+150000 -> 925000 | I3: 904000 | J3: 775000 | K3: =775000+150000 -> 925000 | L3: 975000 | M3: =975000+150000 -> 1125000 | N3: =160000+975000 -> 1135000 | O3: 750000 | P3: =775000+150000 -> 925000
A5: Orchestre de Chambre de Genève | B5: Genève | D5: 100000 | E5: 150000 | F5: 150000 | G5: 150000 | H5: 150000 | I5: 150000 | J5: 150000 | K5: 350000 | L5: 350000 | M5: 350000 | N5: =450000+3000 -> 453000 | O5: 400000 | P5: 500000
A6: Orchestre de Chambre de Lausanne | B6: Vaud | D6: 220000 | E6: 220000 | F6: 220000 | G6: 230000 | H6: 220000 | I6: 440000 | J6: 220000 | K6: 226000 | L6: 200000 | M6: 200000 | N6: 220000 | O6: 250000 | P6: 260000
A7: Orchestre de Chambre fribourgeois | B7: Fribourg | D7: 300000 | E7: 320000 | F7: 320000 | G7: 400000 | H7: 400000 | I7: 400000 | J7: 430000 | K7: 400000 | L7: 410000 | M7: 410000 | N7: 410000 | O7: =425000+9100 -> 434100 | P7: 435500
A9: Fond. OSR, Genève | B9: Genève | D9: 500000 | E9: =260000+500000 -> 760000 | F9: =500000 -> 500000 | G9: 300000 | H9: 400000 | I9: 400000 | J9: 400000 | K9: 300000 | L9: =400000 -> 400000 | M9: 450000 | N9: =200000+90000 -> 290000 | O9: 350000 | P9: 317600
A10: Assoc. vaudoise des Amis de l’Orchestre de la Suisse Romande - AVAOSR | E10: 105000 | F10: 105000 | G10: 95000 | H10: 90000 | J10: 90000 | K10: 95000 | M10: 90000 | N10: 90000 | P10: 100000
A11: Fond. de l'Orchestre de la Suisse Romande | O11: 100000 | P11: 120000

Sheet Subv_Festival Cinéma
B1: Canton | D1: 2013 | E1: 2014 | F1: 2015 | G1: 2016 | H1: 2017 | I1: 2018 | J1: 2019 | K1: 2020 | L1: 2021 | M1: 2022 | N1: 2023 | O1: 2024 | P1: 2025
A2: FIFF | D2: 570000 | E2: 570000 | F2: 570000 | G2: 570000 | H2: 570000 | I2: 580000 | J2: 570000 | K2: 580000 | L2: =580000+250000 -> 830000 | M2: =580000 -> 580000 | N2: =215000+580000 -> 795000 | O2: =580000+75000 -> 655000 | P2: =660000+175000 -> 835000
A3: NIFFF | D3: 190000 | E3: 200000 | F3: 210000 | G3: 230000 | H3: 250000 | I3: 250000 | J3: 280000 | K3: 300000 | L3: 283000 | M3: 350000 | N3: 350000 | O3: 350000 | P3: 375000
A4: GIFF | D4: 350000 | E4: 350000 | F4: 350000 | G4: 350000 | H4: 390000 | I4: 350000 | J4: 300000 | K4: 300000 | L4: 300000 | M4: 300000 | N4: 300000 | O4: 300000 | P4: 380000
A5: FIFDH | D5: 300000 | E5: 300000 | F5: 300000 | G5: 300000 | H5: 300000 | I5: 300000 | J5: 300000 | K5: 300000 | L5: 300000 | M5: 400000 | N5: 300000 | O5: =350000 -> 350000 | P5: 400000

Sheet Subv_divers
B1: Canton | D1: 2013 | E1: 2014 | F1: 2015 | G1: 2016 | H1: 2017 | I1: 2018 | J1: 2019 | K1: 2020 | L1: 2021 | M1: 2022 | N1: 2023 | O1: 2024 | P1: 2025
A3: Fond. Salle de concerts et Congrès Sion | B3: Valais | H3: 3000000 | P3: 240000
A4: Switzerland for UNHCR | B4: Genève | O4: 1500000
A5: Fond. pour la Rénovation de la Caserne de la Garde Suisse Pontificale au Vatican | B5: Fribourg | L5: 50000
A6: Transports publics fribourgeois Holding (TPF) SA | B6: Fribourg | L6: 50000
A8: Fond. du Stade de Genève | G8: 600000 | K8: 100000 | L8: 384000
A9: Commune de Sion - Mise en conformité Stade de Tourbillon | H9: 150000
A10: Commune d’Yverdon-les-Bains Stade municipal | N10: 521398 | P10: 140000
A12: Jura Tourisme | B12: Jura | D12: 335000 | E12: 320000 | F12: 345000 | G12: 300000 | H12: 300000 | I12: 300000 | J12: 330000 | K12: 330000 | L12: =300000+120000 -> 420000 | M12: 300000 | N12: 300000 | O12: 300000 | P12: 320000
A13: Valais/Wallis Promotion | B13: Valais | E13: 500000 | F13: 500000 | G13: 500000 | H13: 500000 | I13: 500000 | J13: 540000 | K13: 500000 | L13: 500000 | M13: 500000 | N13: 500000 | O13: 500000 | P13: 500000
A14: Vaud Promotion | B14: Vaud | D14: 1000000 | E14: 1000000 | F14: 1000000 | G14: 1000000 | H14: 1000000 | I14: 1000000 | J14: 1000000 | K14: 1000000 | L14: 1000000 | M14: 1000000 | N14: 1000000 | O14: 1000000 | P14: 1000000
A17: Ski-Club Gendarmerie Vaudoise | B17: Vaud | D17: 16600
A18: Vélo-Club de la Police cant. vaudoise | B18: Vaud | D18: 500 | E18: 500 | F18: 500 | G18: 500
A19: Commission sportive suisse de police - Champ. dEurope de ski de la police aux Diablerets | B19: Vaud | D19: 6000
A20: Police Cantonale Vaudoise Journée sportive de la Police cantonale au Centre sportif de Vallorbe | B20: Vaud | D20: 1000 | E20: 1000 | F20: 1000 | I20: 1000 | N20: 1000 | P20: 1000
A21: Comm. sportive suisse de Police Soutien complémentaire pour lorg. du Champ. dEurope de ski | B21: Vaud | D21: 4000
A22: Fanfare de la Police cantonale valaisanne | B22: Valais | E22: 4000 | N22: 10000
A23: Championnat suisse de judo police | B23: Vaud | F23: 1000 | H23: 1000
A24: Match Suisse-Finlande qualificatif pour les Champ. d’Europe football police | B24: Vaud | H24: 400
A25: Chorale de la Police fribourgeoise | B25: Fribourg | H25: 10000
A26: Groupement Sportif de la Police Cantonale Vaudoise | B26: Vaud | I26: 2000 | M26: 1000
A27: Police cantonale section III Festival suisse des musiques de police 2023 | B27: Jura | M27: 7000
A28: FC police judiciaire | B28: Neuchâtel | O28: 630
A31: Interprofession de la Vigne et du Vin du Valais | B31: Valais | D31: 150000 | E31: 150000 | F31: 150000 | G31: 150000 | H31: 150000 | I31: 150000 | J31: 150000 | K31: 150000 | L31: 225000 | M31: 225000 | N31: 200000 | O31: 200000 | P31: 200000
A34: Athlétissima | B34: Vaud | D34: 60000 | E34: 120000 | F34: 55000 | G34: 5000 | H34: 60000 | I34: 70000 | J34: 70000 | K34: 108000 | L34: 90000 | M34: 70000 | N34: 92000 | O34: 140000 | P34: =88000+50000 -> 138000
A36: Fonds d’utilité publique du Gouvernement | B36: Jura | D36: 1260817 | E36: 1252335 | F36: 1234695 | G36: 1245834 | H36: 1275116 | I36: 1244451 | J36: 1227065 | K36: 1268887 | L36: 1200256.8 | M36: 1517719 | N36: 1107516 | O36: 1414345 | P36: 1660101
A37: Détail dispo | D37: non | E37: non | F37: non | G37: non | H37: non | I37: non | J37: non | K37: non | L37: oui | M37: part | N37: oui | O37: oui | P37: oui
A38: Associations à définir par le Gouvernement > Guerre en Ukraine | M38: 80000
A39: Marché-Concours national de chevaux - Prix du Gouvernement | M39: 3000 | N39: 3000 | O39: 3000 | P39: 3000
